{"t0": {"id": "1216498866717110273", "username": "wellness_jk", "date": "2020-01-12 23:15:05+00:00", "text": "Not tomorrow. Not in a month. Right now. #Vegan #Motivation #mondaythoughts #healthylifestyle #plantbased #wellness #nutrition #HealthyFood #success #Food #Diet #recipespic.twitter.com/YJOK4WoDJt", "label": 1}, "t1": {"id": "1216491130440704000", "username": "dendog43", "date": "2020-01-12 22:44:21+00:00", "text": "Oh dear, as if we didn\u2019t know! @ruthdianecotter @judi_francis @Rhianno18150672 @davidmatheson27https://twitter.com/BeachMilk/status/1216290966564245504 \u2026", "label": 0}, "t2": {"id": "1216488466147504128", "username": "SamStewartAU", "date": "2020-01-12 22:33:46+00:00", "text": "From Discover on Googlehttps://www.abc.net.au/news/2020-01-13/australian-warship-heads-to-iran/11861546 \u2026", "label": 0}, "t3": {"id": "1216483123581480960", "username": "JoshRobinson00", "date": "2020-01-12 22:12:32+00:00", "text": "WOW @POPPY\u2019S NEW ALBUM IS FANTASTIC", "label": 1}, "t4": {"id": "1216482963430367232", "username": "Jacurtis95", "date": "2020-01-12 22:11:54+00:00", "text": "And the worst of them allpic.twitter.com/8vOQQ3fBYy", "label": -1}, "t5": {"id": "1216482149890609152", "username": "peri_coleman", "date": "2020-01-12 22:08:40+00:00", "text": "@JoeKaeser I urge Siemens to rise up to their responsibility & to withdraw from the Adani coal mining development in the Galilee Basin, AUSTRALIA. We know there is only one acceptable way to go: #StopAdani The world is on fire & all are asked to act accordingly", "label": 0}, "t6": {"id": "1216480240052031488", "username": "rachsig", "date": "2020-01-12 22:01:04+00:00", "text": "Virgin Suicides", "label": 0}, "t7": {"id": "1216478892178866177", "username": "rachsig", "date": "2020-01-12 21:55:43+00:00", "text": "I find it so disturbing how so many baby brands are OK with portraying only white & affluent motherspic.twitter.com/S564KY1dwG", "label": 0}, "t8": {"id": "1216476329282957312", "username": "Jacurtis95", "date": "2020-01-12 21:45:32+00:00", "text": "Meanwhile in South Australia we have the same racist name but twicepic.twitter.com/dSlcYySm90", "label": 0}, "t9": {"id": "1216470691437957120", "username": "UniverseOfBetty", "date": "2020-01-12 21:23:08+00:00", "text": "I feel really vulnerable today. Not sure why", "label": 0}, "t10": {"id": "1216469683630694401", "username": "MichalNagy9", "date": "2020-01-12 21:19:08+00:00", "text": "Innocent people die in wars, but it's the animals who're dying right now because of greediness of man's souls and human stupidityhttps://youtu.be/ONDQdvX7y3g", "label": -1}, "t11": {"id": "1216467440810348544", "username": "JoshRobinson00", "date": "2020-01-12 21:10:13+00:00", "text": "The Hamster Dance Song by Hamster Dance Masters is a fucking TUNE don\u2019t even think to @me.", "label": 0}, "t12": {"id": "1216466887845933056", "username": "JoshRobinson00", "date": "2020-01-12 21:08:01+00:00", "text": "The bigger the better, right?", "label": 0}, "t13": {"id": "1216466178173882368", "username": "JoshRobinson00", "date": "2020-01-12 21:05:12+00:00", "text": "This is good!!!!", "label": 1}, "t14": {"id": "1216465978944475137", "username": "RainbowRooAus", "date": "2020-01-12 21:04:24+00:00", "text": "Queer quote of the Day The truth is, there is no one way to \"Come Out\" or be \"Out\". Please Like Share Comment #JoeytheRainbowRoo #QueerQuotepic.twitter.com/tq9JA6ZONE", "label": 1}, "t15": {"id": "1216451143414341632", "username": "JoshRobinson00", "date": "2020-01-12 20:05:27+00:00", "text": "HERE WE GO OMG YESSSSS @DitsOnWrestlingpic.twitter.com/N16R0gb32n", "label": 0}, "t16": {"id": "1216432921734717446", "username": "astro_luca", "date": "2020-01-12 18:53:03+00:00", "text": "Australia fires: lives, hopes, dreams in ashes.pic.twitter.com/UeliRTEA4f", "label": 1}, "t17": {"id": "1216421473386205188", "username": "ivanavica", "date": "2020-01-12 18:07:33+00:00", "text": "Proud of these guys!!! #ATPCup #TeamSerbia We love you pic.twitter.com/zVueqZv0KC", "label": 1}, "t18": {"id": "1216377177693773837", "username": "MissMCatlady", "date": "2020-01-12 15:11:33+00:00", "text": "Where does it say \u2018all\u2019 ? I was referring to fire starters", "label": 0}, "t19": {"id": "1216359330175471618", "username": "AlexsWRLD15", "date": "2020-01-12 14:00:37+00:00", "text": "just wanna put it out there @jschlatt @Misfits @goopmediapic.twitter.com/5wtJArpDLh", "label": 0}, "t20": {"id": "1216354818035290112", "username": "gilhick", "date": "2020-01-12 13:42:42+00:00", "text": "I mainly need to go to sleep But I also mainly need to find out the winner between @theoldnunshead and @ivyhousenunhead in @deserterblog World Cup of Pubs #worldcupofpubs", "label": 1}, "t21": {"id": "1216353392575963137", "username": "RacingNielsen", "date": "2020-01-12 13:37:02+00:00", "text": "A very well deserved win for this guy today Congratulations again @CNobleracing https://twitter.com/CNobleracing/status/1216312782297145347 \u2026", "label": 1}, "t22": {"id": "1216350493041029121", "username": "JoshRobinson00", "date": "2020-01-12 13:25:30+00:00", "text": "That is my goal, always", "label": 0}, "t23": {"id": "1216347895575629826", "username": "JoshRobinson00", "date": "2020-01-12 13:15:11+00:00", "text": "I cannot even begin to explain how much means nice words like that mean to me. So instead, here is a GIF of the IIconics being IIconic.pic.twitter.com/hlIsPvB2cP", "label": 1}, "t24": {"id": "1216347098741792768", "username": "abhishekkmedhi", "date": "2020-01-12 13:12:01+00:00", "text": "You always Gain by giving love .pic.twitter.com/m118dYuB3k", "label": 1}, "t25": {"id": "1216344061105147904", "username": "chriscooper86", "date": "2020-01-12 12:59:57+00:00", "text": "Huge day today, Caiguna to Minnipa. Another big day ahead tomorrow to get to Coober Pedy for the the night. Then a quick search for Taipans before heading on for Uluru! #SydneyBound #RoadTrip #CarCampingpic.twitter.com/Q5ZRHJYJzq", "label": 0}, "t26": {"id": "1216340246326984704", "username": "BlackDouglas", "date": "2020-01-12 12:44:47+00:00", "text": "I'm devastated!!https://twitter.com/AusIndiMedia/status/1216296915479846915 \u2026", "label": 0}, "t27": {"id": "1216339245725409281", "username": "BlackDouglas", "date": "2020-01-12 12:40:49+00:00", "text": "Fish kills! Dead forests! Soon a dead Reef!!https://twitter.com/AnnieOdyne/status/1216338806552420355 \u2026", "label": -1}, "t28": {"id": "1216334366172860416", "username": "Jacurtis95", "date": "2020-01-12 12:21:25+00:00", "text": "Ask it politely to move away", "label": 0}, "t29": {"id": "1216333839414333440", "username": "Jacurtis95", "date": "2020-01-12 12:19:20+00:00", "text": "CW: suicide A teacher at my school made a comment about how suicide is \u201cthe coward\u2019s way out\u201d to a class where one of the girl\u2019s dad had literally committed suicide a couple months prior Also he got busted for child porn a few years laterhttps://twitter.com/roxannewoIf/status/1215118710605799427 \u2026", "label": -1}, "t30": {"id": "1216332056541585408", "username": "JoshRobinson00", "date": "2020-01-12 12:12:15+00:00", "text": "Thanks dude, im shocked!", "label": 0}, "t31": {"id": "1216330597825560577", "username": "Leeshalicious_", "date": "2020-01-12 12:06:27+00:00", "text": "What proposal? They didn't even let Ian ask or let Mickey get his proposal! AND what was with cutting off the kiss? I wanted a club kiss 2.0 This was such a let down.https://twitter.com/mickeysianx/status/1216246652203425792 \u2026", "label": 1}, "t32": {"id": "1216327174816272384", "username": "KhamaGilchrist", "date": "2020-01-12 11:52:51+00:00", "text": "Hey, don't yell in a library. It's like, the one rule.", "label": 0}, "t33": {"id": "1216326568856842240", "username": "dendog43", "date": "2020-01-12 11:50:26+00:00", "text": "Yeah, Crowey is a bit of a dill when he has to write his own scripts.https://twitter.com/quelineruby64/status/1216277810878148608 \u2026", "label": 0}, "t34": {"id": "1216325546478424064", "username": "dendog43", "date": "2020-01-12 11:46:23+00:00", "text": "I love the term \u201cclimate deniers\u201d Wtf does it mean? There\u2019s nothing to deny. Climate has been happening since the Big Bang @ruthdianecotter @Rhianno18150672 @davidmatheson27 @judi_francishttps://twitter.com/BawdenSnoek/status/1216235622848819200 \u2026", "label": 0}, "t35": {"id": "1216324335251550208", "username": "dendog43", "date": "2020-01-12 11:41:34+00:00", "text": "Miranda is spot on again. As usual @davidmatheson27 @judi_francishttps://twitter.com/WayneK5911/status/1216257096582217733 \u2026", "label": 0}, "t36": {"id": "1216323792642834432", "username": "dendog43", "date": "2020-01-12 11:39:25+00:00", "text": "If they are white Aussies they\u2019ll go down for a couple of months community service. If they are refugees/immigrants we will pay them compensation and apologise for the inconvenience Happy to be proven wronghttps://twitter.com/826Maureen/status/1216243151733587968 \u2026", "label": 1}, "t37": {"id": "1216322982945030144", "username": "dendog43", "date": "2020-01-12 11:36:11+00:00", "text": "Yes, there\u2019s more than just plain incompetence going on here. Imagine those idiots with a nuclear capability? They\u2019d make North Korea look like a kindergarten picnic @davidmatheson27 @judi_francis @Rhianno18150672 @ruthdianecotterhttps://twitter.com/mishtal/status/1216050013589118983 \u2026", "label": 0}, "t38": {"id": "1216322318768590853", "username": "wcsentinel", "date": "2020-01-12 11:33:33+00:00", "text": "Spot fires flare in Kangaroo Island bushfire, scenes of devastation, advice warning extends east http://www.westcoastsentinel.com.au/story/6576680/spot-fires-flare-in-kangaroo-island-bushfire-scenes-of-devastation-advice-warning-extends-east/?src=rss \u2026pic.twitter.com/EBMFYBTdBx", "label": -1}, "t39": {"id": "1216316765677834240", "username": "JoshRobinson00", "date": "2020-01-12 11:11:29+00:00", "text": "Cheers to @RichBakerDraws for the AWESOME new @JoshRobinson00 and #JoshPlays logos!pic.twitter.com/HL88xvxpre", "label": 1}, "t40": {"id": "1216309554616496128", "username": "Schodes_", "date": "2020-01-12 10:42:50+00:00", "text": "The last few weeks have been nothing short of amazing. Holidays spent with my beautiful family and memories made that will last a lifetime. I miss everything already #blood #eyerpeninsula #louthbay #portlincoln\u2026 https://www.instagram.com/p/B7N3ZorlxO_/?igshid=1vqlctqmdau4g \u2026", "label": 0}, "t41": {"id": "1216307158981021697", "username": "MissMCatlady", "date": "2020-01-12 10:33:19+00:00", "text": "& being compared to Hitler Youth", "label": 0}, "t42": {"id": "1216306833222012928", "username": "MissMCatlady", "date": "2020-01-12 10:32:01+00:00", "text": "I can\u2019t unsee this .. I hate some humans", "label": -1}, "t43": {"id": "1216306713114173441", "username": "Fallon_84", "date": "2020-01-12 10:31:32+00:00", "text": "Love your work ABC journo loving our Drag Storytimehttps://www.facebook.com/127304080643826/posts/3543518269022373/ \u2026", "label": 1}, "t44": {"id": "1216302082963185664", "username": "same_weather", "date": "2020-01-12 10:13:09+00:00", "text": "Andamooka Airport, Australia - Arly Airport, Burkina Faso ADO-ARL Weather (Mon): clear-day/28\u00b0C", "label": 0}, "t45": {"id": "1216300462883794944", "username": "CuddliesCo", "date": "2020-01-12 10:06:42+00:00", "text": "For the love of green Outrageously soft, #eco bamboo nappies and wet wipes. #bamboonappies #believeinbetterpic.twitter.com/QYV9Rr06YT", "label": 0}, "t46": {"id": "1216297132958707714", "username": "marvinosifo", "date": "2020-01-12 09:53:28+00:00", "text": "There will always be light and dark in this world, yet if we focus too much on the darkness, it\u2019ll bring our energy down. We have to try to see the good, to listen to positive news and to surround ourselves with love and joy if we want to live a pleasant life.", "label": 1}, "t47": {"id": "1216293873493794816", "username": "BryanGarris_", "date": "2020-01-12 09:40:31+00:00", "text": "Never heard of the last one, so I\u2019ll let it slide.", "label": 0}, "t48": {"id": "1216291953437863936", "username": "benpratt9", "date": "2020-01-12 09:32:53+00:00", "text": "@1629senSA any chance you can get a more powerful transmitter so people past Gepps Cross can listen in to the @BBL", "label": 1}, "t49": {"id": "1216290711462539265", "username": "RacingNielsen", "date": "2020-01-12 09:27:57+00:00", "text": "Podium: The outtakes #4HTheBend | #AsianLeMans @CNobleracing @WeAreTeamMerit @PIM_Motorsport @AsianLMSpic.twitter.com/iTObE0Dmfj", "label": 0}, "t50": {"id": "1216286024000819200", "username": "TheCandyKaine", "date": "2020-01-12 09:09:20+00:00", "text": "Oh this turned out frumpier than I expected", "label": 0}, "t51": {"id": "1216281833966432256", "username": "KhamaGilchrist", "date": "2020-01-12 08:52:41+00:00", "text": "Spare a moment for the media teams of seasonal sports. The down time must be rough.https://twitter.com/Adelaide_FC/status/1216276125145452544 \u2026", "label": 0}, "t52": {"id": "1216277014476275712", "username": "wcsentinel", "date": "2020-01-12 08:33:32+00:00", "text": "Spot fires flare in Kangaroo Island bushfire, scenes of devestation, advice warning extends east http://www.westcoastsentinel.com.au/story/6576680/spot-fires-flare-in-kangaroo-island-bushfire-scenes-of-devestation-advice-warning-extends-east/?src=rss \u2026pic.twitter.com/pDgueMpStq", "label": 0}, "t53": {"id": "1216277014291705857", "username": "EyreTribune", "date": "2020-01-12 08:33:32+00:00", "text": "Spot fires flare in Kangaroo Island bushfire, scenes of devastation, advice warning extends east http://www.eyretribune.com.au/story/6576680/spot-fires-flare-in-kangaroo-island-bushfire-scenes-of-devastation-advice-warning-extends-east/?src=rss \u2026pic.twitter.com/SZzk11UxUn", "label": -1}, "t54": {"id": "1216275891803713536", "username": "dendog43", "date": "2020-01-12 08:29:04+00:00", "text": "21 rapes on average reported. Sources estimate it is six times greaterhttps://twitter.com/PeterSweden7/status/1216076336558673920 \u2026", "label": -1}, "t55": {"id": "1216274975272751104", "username": "dendog43", "date": "2020-01-12 08:25:26+00:00", "text": "Well, #ScoMo is 100% correct. I\u2019m not normally one for tautologies but this calls for an extreme response. Speers, as usual showed scant regard for facts and seemed intent on wedging our PM @davidmatheson27 @judi_francis @Colin_J_Pottshttps://twitter.com/annabelcrabb/status/1216115316779966464 \u2026", "label": 0}, "t56": {"id": "1216274194868002817", "username": "JohannaGarnett", "date": "2020-01-12 08:22:19+00:00", "text": "Sunday stroll with visitors from the UK...First time they have been to SA and commented that all the parks and historic buildings were second to none and such a glorious surprise @BotGardensSA #history @CityofAdelaide #hiddengempic.twitter.com/pIVj55PWNQ", "label": 1}, "t57": {"id": "1216269376141185025", "username": "KingxRusty", "date": "2020-01-12 08:03:11+00:00", "text": "So upset I won't make it home in time to see Kublai again tonight! Highlight of the weekend tho!!https://twitter.com/GabeThePigeon/status/1216194161524736001 \u2026", "label": 0}, "t58": {"id": "1216267159380168705", "username": "JeamesG", "date": "2020-01-12 07:54:22+00:00", "text": "@JeffreeStar just saw your video & thought you use this Check out this playlist on Amazon Music: love hurtshttps://music.amazon.com.au/user-playlists/d6f549b38b8c4f1bbbc349561a651deca0u0?ref=dm_sh_QIqratw0lh1rbfM6Zl7dmYQvM \u2026", "label": 1}, "t59": {"id": "1216266767326015494", "username": "WolfLSU", "date": "2020-01-12 07:52:49+00:00", "text": "Loved and safe", "label": 1}, "t60": {"id": "1216255757424873473", "username": "dendog43", "date": "2020-01-12 07:09:04+00:00", "text": "The beginning of the end in other words?https://twitter.com/SimonCotter62/status/1216152190328295424 \u2026", "label": 0}, "t61": {"id": "1216252868291751938", "username": "Jacurtis95", "date": "2020-01-12 06:57:35+00:00", "text": "I\u2019m gonna miss living in that house", "label": 0}, "t62": {"id": "1216252733952532480", "username": "Jacurtis95", "date": "2020-01-12 06:57:03+00:00", "text": "John Wick", "label": 0}, "t63": {"id": "1216251549028159489", "username": "Officialvickmos", "date": "2020-01-12 06:52:20+00:00", "text": "I have finally learn how to toast a girl. Check this out \"Babe as I set my eyes on u, my slippers cut\"", "label": 0}, "t64": {"id": "1216251280433217537", "username": "Officialvickmos", "date": "2020-01-12 06:51:16+00:00", "text": "Most of the SKINNY Girls eat 5 to 12 times a day...and the food goes straight to their attitude", "label": 0}, "t65": {"id": "1216250734985039872", "username": "Officialvickmos", "date": "2020-01-12 06:49:06+00:00", "text": "If garri can sell more than indomie without any advert, My sisters you can get a good man without pretends or dressing half naked Pls Slow down...", "label": 1}, "t66": {"id": "1216250133198917637", "username": "Officialvickmos", "date": "2020-01-12 06:46:43+00:00", "text": "Big Boobs are only attractive inside a bra. Remove the bra and see how the walls of Jericho collapse", "label": 0}, "t67": {"id": "1216249458200956928", "username": "SITechTools", "date": "2020-01-12 06:44:02+00:00", "text": "All features for much affordable price. *Learn more > https://sitechtools.com pic.twitter.com/X3kZ4sWBWE", "label": 0}, "t68": {"id": "1216242829699141632", "username": "KhamaGilchrist", "date": "2020-01-12 06:17:41+00:00", "text": "My brother just told me dishwashing liquid is used by the government to make people sick for population control, and I just had to walk away.pic.twitter.com/WUHCfQz6gM", "label": -1}, "t69": {"id": "1216242012292145155", "username": "RacingNielsen", "date": "2020-01-12 06:14:27+00:00", "text": "Just over an hour of uninterrupted green running, but with 22 minutes to go, there\u2019s more trouble for the GT class - it\u2019s another FCY #4HTheBend | #AsianLeMans", "label": 0}, "t70": {"id": "1216241163201462272", "username": "MissMCatlady", "date": "2020-01-12 06:11:04+00:00", "text": "Can I copy for mine ? Really good !", "label": 1}, "t71": {"id": "1216240485078986752", "username": "RacingNielsen", "date": "2020-01-12 06:08:22+00:00", "text": "Just 30 minutes remain of #4HTheBend @CNobleracing continues to build upon his incredible LMP3 class lead - which currently stands at just under a minute. Who wants to give Tony the good news? #AsianLeManspic.twitter.com/2Cl0it7RJ6", "label": 0}, "t72": {"id": "1216236073279352837", "username": "SMikic13", "date": "2020-01-12 05:50:51+00:00", "text": "Jack Newnes could be the one for @CarltonFC", "label": 0}, "t73": {"id": "1216235073227198464", "username": "SMikic13", "date": "2020-01-12 05:46:52+00:00", "text": "Separation is the only way", "label": 0}, "t74": {"id": "1216234624747130880", "username": "SMikic13", "date": "2020-01-12 05:45:05+00:00", "text": "Prized tickets these will be.... #BushfireCricketBash #BBL09https://www.cricket.com.au/news/bushfire-relief-charity-t20-match-ricky-ponting-shane-warne-gilchrist-lee-bbl-final-big-bash-league/2020-01-12 \u2026", "label": 1}, "t75": {"id": "1216232124140773376", "username": "RacingNielsen", "date": "2020-01-12 05:35:09+00:00", "text": "Job done @CNobleracing squeezes past the Villorba Corse class-rival out the back of the track. Half a second back at the end of the last lap and already 1.7secs clear. 50 laps complete. 66 minutes until #4HTheBend | #AsianLeManspic.twitter.com/DeHZVxRtDp", "label": 0}, "t76": {"id": "1216232090972434433", "username": "donn1821", "date": "2020-01-12 05:35:01+00:00", "text": "Lunch at John\u2019s Mom\u2019s place... It\u2019s one of the things I am going to miss when I go back to the Philippines - to spend my Sunday afternoon at my sister\u2019s mother-in-law\u2019s house. It was nice having unique Greek\u2026 https://www.instagram.com/p/B7NULdAny3h/?igshid=164ohtm8ajs9z \u2026", "label": 0}, "t77": {"id": "1216228531258019840", "username": "ekl99swift", "date": "2020-01-12 05:20:52+00:00", "text": "I finally managed to order a signed copy of Rare. I\u2019M SO EXCITED!! Thank you @selenagomez, LOVE YOU SO MUCH XOXO #Rarepic.twitter.com/kU4GsbRcND", "label": 1}, "t78": {"id": "1216228162138341376", "username": "RacingNielsen", "date": "2020-01-12 05:19:24+00:00", "text": "Unfortunate timing of the FCY finish meant the #12 P3 Ligier was able to pass us whilst @CNobleracing pitted. Know what\u2019s more unfortunate? Quick lap times. Luckily, Colin\u2019s lapping 4secs faster than current class leader Lancieri #4HTheBend | #AsianLeManspic.twitter.com/irEk2wswoI", "label": 0}, "t79": {"id": "1216228150012567552", "username": "RickWareRacing", "date": "2020-01-12 05:19:22+00:00", "text": "Glad everyone is okay! Great work by @thebend_msp Fire Marshals! https://twitter.com/AsianLMS/status/1216226802269446146 \u2026", "label": 1}, "t80": {"id": "1216224025266941952", "username": "RacingNielsen", "date": "2020-01-12 05:02:58+00:00", "text": "144 minutes of running complete and it\u2019s yet another FCY call during this four-hour @AsianLMS race @CNobleracing continues to lead the LMP3 class down under from inside the top ten overall #4HLeMans | #AsianLeMans", "label": 0}, "t81": {"id": "1216222327999827968", "username": "lukejgosling", "date": "2020-01-12 04:56:13+00:00", "text": "SHE does not have a formal qual but has a good b/s radar", "label": 1}, "t82": {"id": "1216220704179249152", "username": "nobbyi333", "date": "2020-01-12 04:49:46+00:00", "text": "So Kev had fires and sold coal while he was PM. Why blame the current PM for the latest natural disaster", "label": -1}, "t83": {"id": "1216220683006427136", "username": "Richardshouse", "date": "2020-01-12 04:49:41+00:00", "text": "Photos don\u2019t do justice to how delicious this beef cheek is!! Great food, Great Wines, Great Location - why wouldn\u2019t you come to the Adelaide Hills!!! @goldingwines #adelaidehillswine @adelhillswine #australiapic.twitter.com/b1stIvMWOS", "label": 1}, "t84": {"id": "1216220627469840384", "username": "MlifestylesD", "date": "2020-01-12 04:49:28+00:00", "text": "If @realDonaldTrump has such advanced war technologys worth trillions of dollars... Why isn't the @usa #government showing any sign of humanity and use there trillion dollars of equipment and go turn out those flames burning a whole d*mn continent #AustralianBushfire #helppic.twitter.com/VSyYif2DpM", "label": 0}, "t85": {"id": "1216219080295772160", "username": "RacingNielsen", "date": "2020-01-12 04:43:19+00:00", "text": "As if we doubted him! LMP3\u2019s fastest runner @CNobleracing reclaims the class lead for the #2 crew. He just needs to keep the #12 Ligier at bay for the next two hours #4HTheBend | #AsianLeManspic.twitter.com/e2nrj8QVO1", "label": 0}, "t86": {"id": "1216218817921085441", "username": "RickWareRacing", "date": "2020-01-12 04:42:17+00:00", "text": "P1 & P2! A little less than 2 hours to go!https://twitter.com/johnnyracer24/status/1216211355956645889 \u2026", "label": 0}, "t87": {"id": "1216217088907309061", "username": "RacingNielsen", "date": "2020-01-12 04:35:24+00:00", "text": "We are GREEN once again at The Bend Let\u2019s go racing! @CNobleracing currently holding P2 with plenty of clear air around and the class leader in the pits. Could it be enough for #2 to reclaim their lead? #4HTheBend | #AsianLeManspic.twitter.com/6HJYuIKRW1", "label": 0}, "t88": {"id": "1216216478829006848", "username": "acton_jus", "date": "2020-01-12 04:32:59+00:00", "text": "You can bet there were other girls who were under age of 16 @VRSVirginia is a witness to this.", "label": 0}, "t89": {"id": "1216213079303700480", "username": "Iamtaryndiaz", "date": "2020-01-12 04:19:28+00:00", "text": "Wanna WIN signed @DisOriginals Merch by @rxdeboymusic ? See my Instagram @Iamtaryndiaz for more! OPEN WORLD WIDE! @DjKnightatl @repost #SCREAMMYNAME #competition #win #RXDEBOYMUSIC #spotify #Instagram #tiktok #likee #creators #trend #viral #followme #dancers #retweet #repostpic.twitter.com/GvsKnVesvr", "label": 1}, "t90": {"id": "1216211274322698241", "username": "RacingNielsen", "date": "2020-01-12 04:12:18+00:00", "text": "SAFETY CAR Just a few minutes of green running here @thebend_msp and the Safety Car has been called out for the burning RLR Oreca. Driver is out and fire extinguished by one of the INCREDIBLE marshalls working this weekend #4HTheBend | #AsianLeManspic.twitter.com/tZCHDadagC", "label": 1}, "t91": {"id": "1216208786538393600", "username": "kate_fegley", "date": "2020-01-12 04:02:25+00:00", "text": ". @CodyShaneWare killingggg it out there! https://twitter.com/RickWareRacing/status/1216207229621137408 \u2026", "label": 0}, "t92": {"id": "1216208451484803072", "username": "MarkRichards_LV", "date": "2020-01-12 04:01:05+00:00", "text": "36 dead, 23 injured in #Cambodia building collapse. Contractor used smaller steel bars than required & removed support scaffold in 10 days instead of 28 days, the PM said. Building's owners charged with unintentional homicide. #WorkSafe #IndustrialManslaughter #OHSreps #CFMMEUhttps://twitter.com/staronline/status/1215896719092617216 \u2026", "label": -1}, "t93": {"id": "1216207750037790720", "username": "RacingNielsen", "date": "2020-01-12 03:58:18+00:00", "text": "Unbelievably, bad luck has struck yet again for the #3 NORMA. Charles Crews has stopped on track. It\u2019s enough to call a FCY across The Bend\u2019s 7.7kms #4HTheBend | #AsianLeManspic.twitter.com/p2zsLUhsTR", "label": -1}, "t94": {"id": "1216206420573442050", "username": "RacingNielsen", "date": "2020-01-12 03:53:01+00:00", "text": "1h15 of running done - time for a pit stop T. Wells @CNobleracing #4HTheBend | #AsianLeManspic.twitter.com/BJqzheGMMH", "label": 0}, "t95": {"id": "1216204547074322432", "username": "RacingNielsen", "date": "2020-01-12 03:45:34+00:00", "text": "Hour 1 Update Wells remains behind the wheel of the #2 NORMA, determined to catch class leader Martin Hippe, whilst Crews continues #3\u2019s recovery drive from last #2 T. Wells | @CNobleracing P2 - 9th overall #3 C. Crews | G.Grist | R. Hodes P4 - 12th overall #4HTheBendpic.twitter.com/NNnbHMHrMb", "label": 1}, "t96": {"id": "1216202538141151234", "username": "RickWareRacing", "date": "2020-01-12 03:37:35+00:00", "text": "Hour is complete @thebend_msp. @CodyShaneWare has moved into the lead in the LMP2 AM class.", "label": 0}, "t97": {"id": "1216200137657044998", "username": "WhatGloriaLoves", "date": "2020-01-12 03:28:03+00:00", "text": "Enjoying a few bottles this weekend", "label": 1}, "t98": {"id": "1216198696733331456", "username": "RacingNielsen", "date": "2020-01-12 03:22:19+00:00", "text": "Pit stops for our LMP3 rivals under that FCY awards Charles Crews\u2019 #3 third in class- so our NORMA M30 duo now run 2-3 with Wells 8secs off the class lead - 3hr20 remain Still plenty of time to pounce! #4HTheBend | #AsianLeManspic.twitter.com/f0PB4BlYMX", "label": 1}, "t99": {"id": "1216195577270005760", "username": "RacingNielsen", "date": "2020-01-12 03:09:56+00:00", "text": "We have our first FCY call to recover debris at T23 after an incident involving Carlin\u2019s Jack Manchester and the D\u2019Station Aston. #2 Wells - P2 (11th overall) #3 Crews - P5 (15th overall) #4HTheBend | #AsianLeManspic.twitter.com/pKhk6C2T7N", "label": 0}, "t100": {"id": "1216191397478334464", "username": "RacingNielsen", "date": "2020-01-12 02:53:19+00:00", "text": "15mins of running under our belts here @thebend_msp Crews has successfully navigated his way through the GT field, and has caught the back of the LMP3 frontrunners. Now the hard work starts from 5th in class Wells has a 4sec gap to close for the class lead. #AsianLeMans", "label": 1}, "t101": {"id": "1216191083534639106", "username": "inverted_soil", "date": "2020-01-12 02:52:04+00:00", "text": "There\u2019s certainly precedent:https://www.csiro.au/en/News/News-releases/2017/Australia-secures-$1-billion-EU-canola-export-market \u2026", "label": 0}, "t102": {"id": "1216189056809234432", "username": "mitchy_price", "date": "2020-01-12 02:44:01+00:00", "text": "thank you", "label": 0}, "t103": {"id": "1216188061693796352", "username": "MissMCatlady", "date": "2020-01-12 02:40:04+00:00", "text": "I gave up ... #singlelife", "label": 0}, "t104": {"id": "1216183994045231105", "username": "RacingNielsen", "date": "2020-01-12 02:23:54+00:00", "text": "Meanwhile, further up the front.. It\u2019s our LMP3 POLE-SITTING #2 NORMA M30. It will be Tony Wells on driver duties when the lights go green here @thebend_msp in less than 10 minutes! #4HTheBend | #AsianLeManspic.twitter.com/gBIvgxfMuA", "label": 0}, "t105": {"id": "1216182978683883521", "username": "busanfan", "date": "2020-01-12 02:19:52+00:00", "text": "So having cleaner local air is of no value ? Does PM stand for Prime Moron?", "label": -1}, "t106": {"id": "1216182184253386752", "username": "RacingNielsen", "date": "2020-01-12 02:16:42+00:00", "text": "Our #3 ready for its comeback drive! Charles Crews will most definitely have his elbows out so watch your mirrors! The view back here isn\u2019t too bad either! Don\u2019t forget, you can watch all the action LIVE : https://youtu.be/qBDFHTibbzI #4HTheBend | #AsianLeManspic.twitter.com/xevkSFEcD2", "label": 0}, "t107": {"id": "1216179358001319937", "username": "Jacurtis95", "date": "2020-01-12 02:05:29+00:00", "text": "Why is deciding what I want to eat the hardest decision for me to make on a daily basis?", "label": 0}, "t108": {"id": "1216175031761264640", "username": "BAMMotorsports", "date": "2020-01-12 01:48:17+00:00", "text": "If you missed the pit walk, head down to the @eurasiaracing garage to grab yours! #4HTheBendhttps://twitter.com/Floodman11/status/1216174021479301120 \u2026", "label": 0}, "t109": {"id": "1216174854170243072", "username": "Jacurtis95", "date": "2020-01-12 01:47:35+00:00", "text": "One pro of having a car is that I can buy ice cream from the shops now and it won\u2019t melt by the time I get home", "label": 0}, "t110": {"id": "1216172086500057089", "username": "JoshRobinson00", "date": "2020-01-12 01:36:35+00:00", "text": "BLESS https://twitter.com/TamasIsland/status/1216083450848899073 \u2026", "label": 1}, "t111": {"id": "1216170944755949568", "username": "RickWareRacing", "date": "2020-01-12 01:32:03+00:00", "text": "Thanks to the awesome fans who came out and joined us for the @AsianLMS Autograph Session! Y\u2019all are the best!pic.twitter.com/nNIyfK1mzs", "label": 1}, "t112": {"id": "1216166931314528256", "username": "rovingblonde", "date": "2020-01-12 01:16:06+00:00", "text": "\u201cBusiness as usual\u201d was criminal negligence and he knew this and ignored and avoided experts (Committee of Australian Fire Chiefs) for the last 6 months! Criminal! #ScoMoResign #AustralianFires #ClimateEmergency #auspolhttps://twitter.com/MurrayWatt/status/1216114371169902593 \u2026", "label": -1}, "t113": {"id": "1216165831719022592", "username": "rovingblonde", "date": "2020-01-12 01:11:44+00:00", "text": "Well this one isn\u2019t surprising. When we see all the racist and the fossil fuel driven parties withdraw too, all will be even more obvious #ScoMoResign #Morrison #auspol #AustralianFires #ClimateEmergencyhttps://twitter.com/vanOnselenP/status/1216118199877373952 \u2026", "label": 0}, "t114": {"id": "1216163408703188992", "username": "MissMCatlady", "date": "2020-01-12 01:02:06+00:00", "text": "@ScottMorrisonMP keeping great companyhttps://twitter.com/JeffreyGuterman/status/1216130400130682886 \u2026", "label": 1}, "t115": {"id": "1216163185494876160", "username": "BarrieCarter6", "date": "2020-01-12 01:01:13+00:00", "text": "There has to be members of the liberal party with the nuts to make a stand on climate change instead of f following like sheep were is this broad church we are told about", "label": 0}, "t116": {"id": "1216162521503023104", "username": "SandyHorne61", "date": "2020-01-12 00:58:34+00:00", "text": "On the upside, that makeup probably does contain sunscreen", "label": 0}, "t117": {"id": "1216161915765870592", "username": "Kangarooei", "date": "2020-01-12 00:56:10+00:00", "text": "Sure ! Thank you for helping the beautiful Wildlife.", "label": 1}, "t118": {"id": "1216161661461004288", "username": "Kangarooei", "date": "2020-01-12 00:55:09+00:00", "text": "Please consider donating to this amazing group, they get food and water to Wildlife throughout Australian bushfire areas so animals who survived can find food and water. Thankyou.https://twitter.com/NeeshNoosh/status/1216160800760586240 \u2026", "label": 1}, "t119": {"id": "1216158017336438784", "username": "PDarbyshire", "date": "2020-01-12 00:40:41+00:00", "text": "That assumes that research And \u2018soundness\u2019 matter any more in policy & decision making https://twitter.com/katekemplin/status/1216040153753452547 \u2026", "label": 0}, "t120": {"id": "1216155337188765696", "username": "AndyCMarshall", "date": "2020-01-12 00:30:02+00:00", "text": "I\u2019ve heard you gotta get out of your comfort zone, but I think this is going a little bit too far", "label": 0}, "t121": {"id": "1216152765535121408", "username": "BarrieCarter6", "date": "2020-01-12 00:19:48+00:00", "text": "Piss weak interview insiders", "label": -1}, "t122": {"id": "1216152652074995712", "username": "RainbowRooAus", "date": "2020-01-12 00:19:21+00:00", "text": "No matter Gay \u200d\u200d\u200d Straight \u200d\u200d\u200d or Bi Lesbian \u200d\u200d\u200d Transgender life I'm on the right track baby I was born to survive Be your Trans self this Australia Day Get yours today https://bit.ly/2tqTfQd Please Like #RainbowRoo #Transgenderpic.twitter.com/LEcX1Jhcbq", "label": 1}, "t123": {"id": "1216152616771579904", "username": "marvinosifo", "date": "2020-01-12 00:19:13+00:00", "text": "We all know the @UGG brand, quintessentially Aussie and famous around the world for their cosy cold weather footwear made from the highest quality wool and materials. #UggExpress #UggAustralia #UGGlifepic.twitter.com/GOs2RDvoiW", "label": 0}, "t124": {"id": "1216152567215841280", "username": "RainbowRooAus", "date": "2020-01-12 00:19:01+00:00", "text": "No matter Gay \u200d\u200d\u200d Straight \u200d\u200d\u200d or Bi Lesbian \u200d\u200d\u200d Transgender life I'm on the right track baby I was born to survive Be your Trans self this Australia Day Get yours today https://bit.ly/2tqTfQd #RainbowRoo #Transgenderpic.twitter.com/0PCXY8J8nD", "label": 0}, "t125": {"id": "1216149603248033793", "username": "BarrieCarter6", "date": "2020-01-12 00:07:15+00:00", "text": "So it's more of the same no gonads from the pentacostal padre", "label": 0}}