{"t0": {"id": "1225569558834053122", "username": "Jacurtis95", "date": "2020-02-06 23:58:47+00:00", "text": "FiveAA caller: \u201care the girls who did the bashing indigenous? not that I want to talk badly about indigenous people, but if they are...\u201d Jesus christ man", "label": 0}, "t1": {"id": "1225562177131732993", "username": "Leeshalicious_", "date": "2020-02-06 23:29:27+00:00", "text": "What if I could click the and choose to have notifs for chapter releases only? It's that a thing?", "label": 0}, "t2": {"id": "1225561892833386498", "username": "Jacurtis95", "date": "2020-02-06 23:28:19+00:00", "text": "Imagining in 40 years time when A Day On The Green features acts like Billie Eilish or Flume", "label": 0}, "t3": {"id": "1225560403876491264", "username": "Jacurtis95", "date": "2020-02-06 23:22:24+00:00", "text": "He was standing up for a disabled person in the group apparently so uuuh pretty problematic of you my man", "label": 0}, "t4": {"id": "1225560042138673152", "username": "adamlea2", "date": "2020-02-06 23:20:58+00:00", "text": "09:30am feeding the baby Kangaroo\u2019s at Cleland Wildlife Park with @ant_917 pic.twitter.com/PqUlKjM7kT", "label": 0}, "t5": {"id": "1225558974923231235", "username": "Jacurtis95", "date": "2020-02-06 23:16:44+00:00", "text": "This is definitely taken out of context but that was the opening line and couldn\u2019t help but laugh", "label": 1}, "t6": {"id": "1225558837928906753", "username": "Jacurtis95", "date": "2020-02-06 23:16:11+00:00", "text": "Somebody texted into FiveAA to say \u201cI\u2019m 45, and recently I got bullied on a Facebook group\u201d", "label": -1}, "t7": {"id": "1225557351165571072", "username": "Jacurtis95", "date": "2020-02-06 23:10:16+00:00", "text": "Like sure they could be paying $700k+ to the 10 people at the top, but they also have heaps of people further below on $50k-$100k annually; it all adds up, and with all the money they make on top of that to make a profit for shareholders... And they barely pay any tax if at all", "label": 1}, "t8": {"id": "1225556601395982341", "username": "Jacurtis95", "date": "2020-02-06 23:07:18+00:00", "text": "When it comes to how much a big business\u2019 top level management are paid, I\u2019ve never really considered that would mean they\u2019re bringing in a fuuuuuuuuuuuck load more money annually than I can even imagine And they barely pay any tax if at all", "label": 0}, "t9": {"id": "1225555270513938436", "username": "BlackDouglas", "date": "2020-02-06 23:02:00+00:00", "text": "Unbelievable isn't it????https://twitter.com/mmbrenn/status/1225555079199166466 \u2026", "label": 0}, "t10": {"id": "1225554922848034816", "username": "BlackDouglas", "date": "2020-02-06 23:00:37+00:00", "text": "REVOLUTION IS IN THE AIR!!https://twitter.com/ChrisBH011/status/1225554716303724545 \u2026", "label": 0}, "t11": {"id": "1225554572866879495", "username": "BlackDouglas", "date": "2020-02-06 22:59:14+00:00", "text": "Logging forests makes them MORE, NOT LESS, FIREPRONE!!https://twitter.com/tilly64/status/1225400991392002050 \u2026", "label": 0}, "t12": {"id": "1225554080837390337", "username": "BlackDouglas", "date": "2020-02-06 22:57:17+00:00", "text": "He thinks the rebels will destroy the party!https://twitter.com/heyjimmy299/status/1225553782731345923 \u2026", "label": -1}, "t13": {"id": "1225553817443454977", "username": "Jacurtis95", "date": "2020-02-06 22:56:14+00:00", "text": "Chikorita was my first and doesn\u2019t suck as much as people say", "label": 0}, "t14": {"id": "1225553324855959560", "username": "ozdivergt", "date": "2020-02-06 22:54:16+00:00", "text": "If you wake to negativity FLIP that thought and love your positive day", "label": 1}, "t15": {"id": "1225553175962361862", "username": "ozdivergt", "date": "2020-02-06 22:53:41+00:00", "text": "Cafe-gate: full video footage, and full audio recording = nowhere to lie or is there?", "label": 0}, "t16": {"id": "1225553124154335243", "username": "BlackDouglas", "date": "2020-02-06 22:53:29+00:00", "text": "That what Tony Windsor thinks too!https://twitter.com/heyjimmy299/status/1225552741784838144 \u2026", "label": 0}, "t17": {"id": "1225552864665313286", "username": "ozdivergt", "date": "2020-02-06 22:52:27+00:00", "text": "How would you feel if you walked in to a cafe and someone who hates you just started taking photos of you? What would you do?", "label": -1}, "t18": {"id": "1225552825045921793", "username": "BlackDouglas", "date": "2020-02-06 22:52:17+00:00", "text": "And speaks with PASSION, even worse!!!https://twitter.com/WilmaSlurrie/status/1225238641502351360 \u2026", "label": 1}, "t19": {"id": "1225552654744551425", "username": "ozdivergt", "date": "2020-02-06 22:51:37+00:00", "text": "Is there trickery in the words the AFP are not investigating Angus Taylor, so are they going after the person who ACTUALLY did the forging?", "label": 0}, "t20": {"id": "1225552636792975361", "username": "BlackDouglas", "date": "2020-02-06 22:51:32+00:00", "text": "So proud of you Kailas!!!https://twitter.com/kailaswild/status/1225372041827639296 \u2026", "label": 1}, "t21": {"id": "1225551799152762880", "username": "BlackDouglas", "date": "2020-02-06 22:48:13+00:00", "text": "We're in a state of unparalleled crisis!https://twitter.com/tagwacheit/status/1225531686252879875 \u2026", "label": 0}, "t22": {"id": "1225551759021608963", "username": "ozdivergt", "date": "2020-02-06 22:48:03+00:00", "text": "Vicky hard at work here inbetween feeds!", "label": 0}, "t23": {"id": "1225551513403187203", "username": "dutchy_nick", "date": "2020-02-06 22:47:05+00:00", "text": "Is it just me or have jacuzzis gone completely out of fashion in the last 10 years?", "label": 0}, "t24": {"id": "1225551229532676099", "username": "ozdivergt", "date": "2020-02-06 22:45:57+00:00", "text": "Did u know 30,000 kids cross the border in to Hong Kong every day to go to school!", "label": 0}, "t25": {"id": "1225550358669336582", "username": "Kangarooei", "date": "2020-02-06 22:42:29+00:00", "text": "Farmers Cull Kangaroos who keep fuel load down. Leave the Kangas instead of destroying them all, it has been open season killing them. Keep the Kangaroos in the National Parks Keep our the Cattke who degrade it. Farmers want it all their way. #NaturesGardeners#Kangaroohttps://twitter.com/Kangarooei/status/1225519971616337927 \u2026", "label": -1}, "t26": {"id": "1225549733172776962", "username": "BlackDouglas", "date": "2020-02-06 22:40:00+00:00", "text": "WE CANNOT LET THIS MATTER REST!!https://twitter.com/Mark_Butler_MP/status/1225286036839747585 \u2026", "label": 0}, "t27": {"id": "1225549536896090112", "username": "BlackDouglas", "date": "2020-02-06 22:39:13+00:00", "text": "Great idea Sharty!https://twitter.com/FlogWarrior/status/1225549257240981505 \u2026", "label": 1}, "t28": {"id": "1225549289423855618", "username": "BlackDouglas", "date": "2020-02-06 22:38:14+00:00", "text": "Agreed!https://twitter.com/heyjimmy299/status/1225549136059076608 \u2026", "label": 0}, "t29": {"id": "1225548654141898752", "username": "BlackDouglas", "date": "2020-02-06 22:35:43+00:00", "text": "I'm pretty sure he's already been judged in the Court of Public Opinion!!https://twitter.com/vanOnselenP/status/1225533639821287424 \u2026", "label": 1}, "t30": {"id": "1225548284946722816", "username": "BlackDouglas", "date": "2020-02-06 22:34:15+00:00", "text": "BIG DOLLARS!!!https://twitter.com/gld301218/status/1225547781470851079 \u2026", "label": 0}, "t31": {"id": "1225545739817947137", "username": "cleverick", "date": "2020-02-06 22:24:08+00:00", "text": "Welcome to the War On Carshttps://twitter.com/anne_theriault/status/1225544153892872198 \u2026", "label": 0}, "t32": {"id": "1225545047195705347", "username": "BlackDouglas", "date": "2020-02-06 22:21:23+00:00", "text": "WE'RE DROWNING IN CORRUPTION!!https://twitter.com/_Oliver_Yates/status/1225533860219359233 \u2026", "label": 0}, "t33": {"id": "1225544749366509568", "username": "BlackDouglas", "date": "2020-02-06 22:20:12+00:00", "text": "When REVOLUTION looms!!!!https://twitter.com/cousincat/status/1225542651321241600 \u2026", "label": 0}, "t34": {"id": "1225544432038096896", "username": "BlackDouglas", "date": "2020-02-06 22:18:56+00:00", "text": "Down the rabbit hole! Our government is killing us!https://twitter.com/mumdaze/status/1225218565055270917 \u2026", "label": -1}, "t35": {"id": "1225542971627593729", "username": "paddykopke", "date": "2020-02-06 22:13:08+00:00", "text": "Esther Henseleit remember the name @LPGA @VicOpenGolf the young German will be a force in the years to come! @BigRandyNLU probably a smoother swing than @Annevandampic.twitter.com/JLtXQWznFr", "label": 0}, "t36": {"id": "1225539502216749057", "username": "BlackDouglas", "date": "2020-02-06 21:59:21+00:00", "text": "I just signed the petition to call on all NSW MPs to not weaken our environmental planning laws. Add your voice today >>>https://www.nature.org.au/get-involved/take-action/don-t-weaken-our-climate-laws/ \u2026", "label": 0}, "t37": {"id": "1225538152431063040", "username": "BlackDouglas", "date": "2020-02-06 21:53:59+00:00", "text": "THEY WORK FOR THE WATER MARKET, NOT THE PEOPLE!!!https://twitter.com/MinnsChris/status/1223798750700658688 \u2026", "label": 0}, "t38": {"id": "1225538127277821958", "username": "ocky1733", "date": "2020-02-06 21:53:53+00:00", "text": "We got a bit last Friday but last year was way down on average .", "label": 0}, "t39": {"id": "1225537639748644864", "username": "BlackDouglas", "date": "2020-02-06 21:51:57+00:00", "text": "YOUR WATER WENT TO BIG COTTON!!https://twitter.com/serehfas/status/1225537382952423424 \u2026", "label": 0}, "t40": {"id": "1225537406998323201", "username": "BlackDouglas", "date": "2020-02-06 21:51:01+00:00", "text": "BURNING COAL CREATES CARBON EMISSIONS! CARBON EMISSIONS IN THE ATMOSPHERE TRAP HEAT: THE GREENHOUSE EFFECT! THIS HAS CAUSED GLOBAL WARMING THAT NOW ENDANGERS THE PLANET JOEL!https://twitter.com/fitzhunter/status/1225524703734968325 \u2026", "label": 0}, "t41": {"id": "1225537341592350722", "username": "abbiebyam", "date": "2020-02-06 21:50:46+00:00", "text": "or artist has either made them happy, smile or save their life. just because they don't like the same music as you doesn't give u any right to be an asshole.", "label": 1}, "t42": {"id": "1225537339813965827", "username": "abbiebyam", "date": "2020-02-06 21:50:45+00:00", "text": "the thing that annoys me souch is the amount of hate the is thrown around 'band fandoms'. Yes you can like whatever the hell you want but NEVER judge someone for their music taste wether it's a band or artist. you don't know what that person has been a lot and that certain band", "label": 0}, "t43": {"id": "1225536606607749121", "username": "BlackDouglas", "date": "2020-02-06 21:47:51+00:00", "text": "HIDEOUS!!https://twitter.com/JodiMcKayMP/status/1225532890756374529 \u2026", "label": 0}, "t44": {"id": "1225536103475765248", "username": "mookie6869", "date": "2020-02-06 21:45:51+00:00", "text": "I am certainly sure I could think of a couple of really quick ideas to getting warm again. An outstanding and so overwhelming Asian beauty", "label": 1}, "t45": {"id": "1225535380302237696", "username": "mookie6869", "date": "2020-02-06 21:42:58+00:00", "text": "Now I\u2019m really really hungry ... let\u2019s eat out.", "label": 0}, "t46": {"id": "1225535193894805506", "username": "mareedam", "date": "2020-02-06 21:42:14+00:00", "text": "Every morning I wake up to seagulls and dogs barking on the beach. That\u2019s regional South Australia for you! IYP #RegionsMatterpic.twitter.com/7AqB89RBjo", "label": 0}, "t47": {"id": "1225535014005354499", "username": "BlackDouglas", "date": "2020-02-06 21:41:31+00:00", "text": "BOUGHT not BULLIED Annie!https://twitter.com/AnnieKia/status/1225534745876017159 \u2026", "label": 1}, "t48": {"id": "1225534909206474752", "username": "peri_coleman", "date": "2020-02-06 21:41:06+00:00", "text": "Some of our \u201cshort squat\u201d Tecticornia arbuscula in SA turn out to be Tecticornia moniliformis, a very similar species from the old Sclerostegia group that tolerates drier, hotter and more saline conditions. Only recently recognised here. #saltmarsh matters", "label": 0}, "t49": {"id": "1225534805431005189", "username": "BlackDouglas", "date": "2020-02-06 21:40:41+00:00", "text": "REVOLTING!!!https://twitter.com/LaLegale/status/1225533059447037952 \u2026", "label": 0}, "t50": {"id": "1225534699382231042", "username": "BlackDouglas", "date": "2020-02-06 21:40:16+00:00", "text": "Well I'm allergic to preservatives, so my diet is VERY restricted!https://twitter.com/LaLegale/status/1225533262916980736 \u2026", "label": 0}, "t51": {"id": "1225534578833657857", "username": "chrisburnettt", "date": "2020-02-06 21:39:47+00:00", "text": "Strangely alluringhttps://twitter.com/RexChapman/status/1225458744265445378 \u2026", "label": 0}, "t52": {"id": "1225534251556319232", "username": "BlackDouglas", "date": "2020-02-06 21:38:29+00:00", "text": "Think outside the square Les! Think GREEN COALITION! A Party of people who promise to mitigate climate change and end corruption!! @AdamBandt @MGliksmanMDPhD @_Oliver_Yates @adamajacoby @drkerrynphelps @simonahachttps://twitter.com/LesStonehouse/status/1225514754048962568 \u2026", "label": 1}, "t53": {"id": "1225533077142884356", "username": "peri_coleman", "date": "2020-02-06 21:33:49+00:00", "text": "Sadly our stands of big old Tecticornia arbuscula (2m tall) at Port Gawler are now nearly all gone. Every time I visit there are less #sea level rise", "label": 0}, "t54": {"id": "1225532941226381318", "username": "BlackDouglas", "date": "2020-02-06 21:33:17+00:00", "text": "We've become a banana republic!https://twitter.com/jommy_tee/status/1225498941300629506 \u2026", "label": 0}, "t55": {"id": "1225532570118639616", "username": "dendog43", "date": "2020-02-06 21:31:48+00:00", "text": "Ok, I can see that. I\u2019m the same with MSM news. Just can\u2019t cope with the continual lefty propaganda Cheers from South Australiahttps://twitter.com/JPattersonAUS/status/1225529790607831041 \u2026", "label": 0}, "t56": {"id": "1225532417068457992", "username": "BlackDouglas", "date": "2020-02-06 21:31:12+00:00", "text": "Tough???https://twitter.com/LaLegale/status/1225518388065251335 \u2026", "label": 0}, "t57": {"id": "1225532301666390016", "username": "BlackDouglas", "date": "2020-02-06 21:30:44+00:00", "text": "Glad we've seen better days eh Michaela!!https://twitter.com/LaLegale/status/1225531772592705537 \u2026", "label": 1}, "t58": {"id": "1225532087043796995", "username": "BlackDouglas", "date": "2020-02-06 21:29:53+00:00", "text": "CORRUPTION? WHAT CORRUPTION? NOTHING TO SEE HERE! MOVE ON PLEASE (SHEEPLE)!!https://twitter.com/liamalexander/status/1225506218237743104 \u2026", "label": 1}, "t59": {"id": "1225531667764436992", "username": "BlackDouglas", "date": "2020-02-06 21:28:13+00:00", "text": "100g meat per serve!https://twitter.com/alan_furey/status/1225419464524517376 \u2026", "label": 0}, "t60": {"id": "1225531112446976002", "username": "BlackDouglas", "date": "2020-02-06 21:26:01+00:00", "text": "We're the plague that destroyed the Planet!!https://twitter.com/43a6f0ce5dac4ea/status/1225430138491297792 \u2026", "label": -1}, "t61": {"id": "1225530773127737352", "username": "BlackDouglas", "date": "2020-02-06 21:24:40+00:00", "text": "Who ARE these people???? Where is their SOUL??https://twitter.com/LaLegale/status/1225518388065251335 \u2026", "label": 0}, "t62": {"id": "1225530414036594698", "username": "cleverick", "date": "2020-02-06 21:23:14+00:00", "text": "Just when I'm going to Melbs!", "label": 0}, "t63": {"id": "1225529018910420996", "username": "dendog43", "date": "2020-02-06 21:17:41+00:00", "text": "So, no Foxtel means you\u2019ll rely on 2, 7, 9, 10 and SBS for your news, current affairs and political viewpoints. You\u2019re a brave person! @judi_francis @davidmatheson27https://twitter.com/JPattersonAUS/status/1224838457253560325 \u2026", "label": 0}, "t64": {"id": "1225528376296910869", "username": "oz_farmer_nerd", "date": "2020-02-06 21:15:08+00:00", "text": "Our Agro uses it and we don\u2019t have an Agworld subscription so he just emails us a PDF of the reco which works really well for me", "label": 0}, "t65": {"id": "1225527370087632898", "username": "ladywhitepeace1", "date": "2020-02-06 21:11:08+00:00", "text": "How can anyone trust the Liberal Party?? It\u2019s the dirtiest lying power hungry organisation in Australia if not the world", "label": 0}, "t66": {"id": "1225527084832960515", "username": "oz_farmer_nerd", "date": "2020-02-06 21:10:00+00:00", "text": "Ha cheeky shit", "label": 0}, "t67": {"id": "1225525031465299978", "username": "MattJelonek", "date": "2020-02-06 21:01:51+00:00", "text": "#WRC and RedBull Photographer shot #RallyeMonteCarlo on film, check out his results here!https://www.redbullcontentpool.com/premium/photography/news/shooting-the-wrc-monte-carlo-on-film \u2026", "label": 0}, "t68": {"id": "1225524066540498948", "username": "ladywhitepeace1", "date": "2020-02-06 20:58:01+00:00", "text": "He is so lucky he\u2019s not my child I would beat him with a strap and and not give him food for 3 days!!https://twitter.com/RobRobbEdwards/status/1225293622167261185 \u2026", "label": 1}, "t69": {"id": "1225521820528529409", "username": "ley_monica", "date": "2020-02-06 20:49:05+00:00", "text": "I know there was a couple that broke down in the first two weeks. It was just a syndicate thrown together. Probably no DNA testing in that maiden mob as it is just commercials but in the stud mobs we do a lot of single mate.", "label": 0}, "t70": {"id": "1225521507662794752", "username": "TravAkbar", "date": "2020-02-06 20:47:51+00:00", "text": "I need to stop thinking of new movies ideas that I want to write, and actually finish the one that was supposed to be finished last year :/", "label": -1}, "t71": {"id": "1225520698405335040", "username": "Kangarooei", "date": "2020-02-06 20:44:38+00:00", "text": "Farmers cull Kangaroos who keep fuel load down. Keep Cattle out of National Parks and leave #Kangaroos to do what they are here for. Farmers want it all, they are in many cases Environmental Vandals with their cattle sheep etc. #Kangaroohttps://twitter.com/Kangarooei/status/1225519971616337927 \u2026", "label": 0}, "t72": {"id": "1225519993036603392", "username": "ppandey007", "date": "2020-02-06 20:41:50+00:00", "text": "looking for a change agent, a people person with attention to detail, who can think outside the box and is passionate about data capture with the focus on business outcomes. Do you have what it takes to lead a team of metadata specialists! If yes @FlindersLib wants you!!https://twitter.com/LizWalkleyHall/status/1225383422052331520 \u2026", "label": 1}, "t73": {"id": "1225519291686105088", "username": "TremyIRL", "date": "2020-02-06 20:39:02+00:00", "text": "Looking for practically a full time editor to pump out my content for YouTube. Drop me a DM #editor #videoeditor #twitch #graphicdesign", "label": 0}, "t74": {"id": "1225516266867318785", "username": "glatzblack", "date": "2020-02-06 20:27:01+00:00", "text": "Could be a Claas Action?", "label": 0}, "t75": {"id": "1225510980093915136", "username": "TremyIRL", "date": "2020-02-06 20:06:01+00:00", "text": "@im_DjL Do you still provide editing services?", "label": 0}, "t76": {"id": "1225509440931160065", "username": "Michellebamo", "date": "2020-02-06 19:59:54+00:00", "text": "A client of mine up there almost got as much rain as they did in 2019! Let\u2019s hope it keeps coming through the season", "label": 0}, "t77": {"id": "1225505700257947649", "username": "ladywhitepeace1", "date": "2020-02-06 19:45:02+00:00", "text": "Poor America big suffering coming your wayhttps://twitter.com/NeonNettle/status/1225500669924212736 \u2026", "label": -1}, "t78": {"id": "1225505574248423424", "username": "Jacurtis95", "date": "2020-02-06 19:44:32+00:00", "text": "huge if true", "label": 1}, "t79": {"id": "1225504618152636417", "username": "ladywhitepeace1", "date": "2020-02-06 19:40:44+00:00", "text": "Mum not Dad you haven\u2019t listened to it or the dodo hasn\u2019t??", "label": 0}, "t80": {"id": "1225491027500380161", "username": "Jacurtis95", "date": "2020-02-06 18:46:44+00:00", "text": "Almost enough people that if they voted for Bernie he\u2019d win", "label": 1}, "t81": {"id": "1225490768263024640", "username": "Jacurtis95", "date": "2020-02-06 18:45:42+00:00", "text": "I can\u2019t wait for this weekend! I\u2019ve told so many people about my road trip to make sure I don\u2019t bail on it, and I\u2019m just really excited to see a part of the state I\u2019ve never been to before!", "label": 1}, "t82": {"id": "1225489942580776961", "username": "Jacurtis95", "date": "2020-02-06 18:42:25+00:00", "text": "Selling yourself out for the ever-changing public opinion is a bad road to go down, and people see through your phoniness people will come with you if you convince them to - the republicans are good at this part because they have less shame and restrictions on what they\u2019ll say", "label": 0}, "t83": {"id": "1225489939477008387", "username": "Jacurtis95", "date": "2020-02-06 18:42:24+00:00", "text": "I think Bernie is the only one that realises that the best way to win is to campaign with authenticity on issues you believe in rather than flipping to what you think people want to hearhttps://twitter.com/aterkel/status/1225483497005035527 \u2026", "label": 1}, "t84": {"id": "1225487944770818048", "username": "Jacurtis95", "date": "2020-02-06 18:34:29+00:00", "text": "Putting this on my timeline is akin to violence imo", "label": -1}, "t85": {"id": "1225482363855163394", "username": "Jacurtis95", "date": "2020-02-06 18:12:18+00:00", "text": "Warner Bros knew exactly what they were doing here", "label": 0}, "t86": {"id": "1225478991047360512", "username": "JeamesG", "date": "2020-02-06 17:58:54+00:00", "text": "I never know how to take these words when coming from a stranger whom makes me happy with videos and merchandise. It just leaves wondering. I respect you @MrBeastYT I admire you, you make me happy but I love you seem like we have to know each other more.https://twitter.com/MrBeastYT/status/1225262651808403456 \u2026", "label": 1}, "t87": {"id": "1225473557813063680", "username": "Jacurtis95", "date": "2020-02-06 17:37:19+00:00", "text": "I try to avoid them", "label": 0}, "t88": {"id": "1225473066123194370", "username": "Jacurtis95", "date": "2020-02-06 17:35:21+00:00", "text": "write a fan fic", "label": 0}, "t89": {"id": "1225471103369457669", "username": "VinicioReina", "date": "2020-02-06 17:27:33+00:00", "text": "Bobby Shultz Beautiful Teen Model https://www.instagram.com/p/B8OJ2aOBSCc/?igshid=1am0liqmiei9o \u2026", "label": 1}, "t90": {"id": "1225451596747878401", "username": "lifeadvicebotto", "date": "2020-02-06 16:10:03+00:00", "text": "Anyway... Can I... get you something?", "label": 0}, "t91": {"id": "1225435251704463367", "username": "jbmoorephoto", "date": "2020-02-06 15:05:06+00:00", "text": "Orphaned wombat Xena, four months old. Now you see me. Now you don\u2019t. #AustraliaOnFire #AustralianwildFires #gettyimages #gettyimagesnews #NWSAustraliapic.twitter.com/I6w54CkJs9", "label": 0}, "t92": {"id": "1225434444195983360", "username": "Jewel62420823", "date": "2020-02-06 15:01:53+00:00", "text": "Try the New Dyson Vacuum Now! https://bit.ly/2S2Ksh3 Dyson vacuum cleaners are engineered to deep clean your home", "label": 0}, "t93": {"id": "1225427780713598978", "username": "Jewel62420823", "date": "2020-02-06 14:35:24+00:00", "text": "Try the New Dyson Vacuum Now! https://bit.ly/3bfS6fR Dyson has continued to innovate vacuum cleaner technology. Engineering upright vacuums that provide powerful suction for a deep clean on all floor types.", "label": 1}, "t94": {"id": "1225422177345900544", "username": "same_weather", "date": "2020-02-06 14:13:08+00:00", "text": "Orientos Airport, Australia - Kolda North Airport, Senegal OXO-KDA Weather (Fri): clear-day/28\u00b0C", "label": 0}, "t95": {"id": "1225418895185498112", "username": "Chey_Marie06", "date": "2020-02-06 14:00:06+00:00", "text": "Living the beach bum life!pic.twitter.com/Jf68PvMbN5", "label": 0}, "t96": {"id": "1225404423700017157", "username": "jennaclaire222", "date": "2020-02-06 13:02:36+00:00", "text": "That\u2019s right bitch, spread that jam niiiiiice and thick.. Mmmm mmmm! pic.twitter.com/OLaPe6nYV1", "label": -1}, "t97": {"id": "1225402574863392768", "username": "BlackDouglas", "date": "2020-02-06 12:55:15+00:00", "text": "CRINGE!!!!!!https://twitter.com/HamishTaylor31/status/1225316948851904512 \u2026", "label": 0}, "t98": {"id": "1225402286601461760", "username": "BlackDouglas", "date": "2020-02-06 12:54:06+00:00", "text": "There will be a deluge of class actions!https://twitter.com/ElaineEDO/status/1225317118482120705 \u2026", "label": 0}, "t99": {"id": "1225401760212062209", "username": "BlackDouglas", "date": "2020-02-06 12:52:01+00:00", "text": "Totally agree!https://twitter.com/OrBVIOUS66/status/1225401381604847617 \u2026", "label": 0}, "t100": {"id": "1225401715555307522", "username": "gah_australia", "date": "2020-02-06 12:51:50+00:00", "text": "Are you finding it hard to get a blue ticked Turnitin report for your assignment? Worry Not!!! Choose our services and get a free Turnitin report with every write-up. Call us: +61283206050 visit us: https://www.globalassignmenthelp.com/ #MEMES #assignmennt #australiapic.twitter.com/yiTk4plDAS", "label": -1}, "t101": {"id": "1225401054394667009", "username": "assignmentprime", "date": "2020-02-06 12:49:12+00:00", "text": "LET\u2019S PRAY FOR THOSE AFFECTED BY CORONA VIRUS. Contact Us @+61879057034 Visit Us@https://www.assignmentprime.com/ #CoronaOutbreak #corononaviruspic.twitter.com/fQCzodq1nH", "label": 0}, "t102": {"id": "1225400970814689280", "username": "BlackDouglas", "date": "2020-02-06 12:48:52+00:00", "text": "God help us all if he succeeds!https://twitter.com/vanOnselenP/status/1225381670292877312 \u2026", "label": 1}, "t103": {"id": "1225399959383470082", "username": "BlackDouglas", "date": "2020-02-06 12:44:51+00:00", "text": "Essential to a healthy diet!!https://twitter.com/sbthatsme123/status/1225399299577483264 \u2026", "label": 1}, "t104": {"id": "1225399645414686725", "username": "BlackDouglas", "date": "2020-02-06 12:43:36+00:00", "text": "We have some serious problems!!https://twitter.com/MingYLong/status/1225199753257816064 \u2026", "label": 0}, "t105": {"id": "1225398936917012487", "username": "BlackDouglas", "date": "2020-02-06 12:40:48+00:00", "text": "They seem to have a problem with green and yellow vegetables, and THE MEAT????https://twitter.com/LaLegale/status/1225394062016028672 \u2026", "label": -1}, "t106": {"id": "1225396838347370498", "username": "BlackDouglas", "date": "2020-02-06 12:32:27+00:00", "text": "I've studied horticulture and lived in a coastal forest for 10 years! I've also just read some 2020 studies on the effects of burning forests! I'll send you some links tomorrow.https://twitter.com/talkingkoala/status/1225395224647614467 \u2026", "label": 0}, "t107": {"id": "1225396231293296640", "username": "eyreimports", "date": "2020-02-06 12:30:02+00:00", "text": "When you\u2019re serious about your health, nutrition and what you put in your body you take control. Organic Superfoods and herbal medicines are often not even produce from organic sources. Vegan capsules that I plant\u2026 https://www.instagram.com/p/B8Obi1ug46x/?igshid=1entl9jqk55uo \u2026", "label": 0}, "t108": {"id": "1225394977993134081", "username": "LauraHillsLamb", "date": "2020-02-06 12:25:04+00:00", "text": "Imagine how expensive grain was before fuel fuels mechanised grain production.", "label": 0}, "t109": {"id": "1225393455993483264", "username": "BlackDouglas", "date": "2020-02-06 12:19:01+00:00", "text": "Not all forests Maria. Wet forests and rain forests don't recover from burning. Fire also changes forests' ecology and ecosystems! The Aboriginals mainly used fire to create grassland for hunting. Coastal heathlands depend on burning.https://twitter.com/talkingkoala/status/1225318286079877120 \u2026", "label": 0}, "t110": {"id": "1225391621761425408", "username": "LauraHillsLamb", "date": "2020-02-06 12:11:43+00:00", "text": "We need to manage grasslands and agricultural land better to sequest carbon into soil. This farm sequested nearly 4T CO2 /ha/yr as SOC and tree biomass.https://www.publish.csiro.au/an/pdf/AN15541", "label": 0}, "t111": {"id": "1225390721848377344", "username": "LauraHillsLamb", "date": "2020-02-06 12:08:09+00:00", "text": "We need huge numbers of paid people to make burns happen. If the window is small we need to make the process more streamlined and have people ready to manage the burn.", "label": 1}, "t112": {"id": "1225389179447599109", "username": "LauraHillsLamb", "date": "2020-02-06 12:02:01+00:00", "text": "I'm all up for reducing carbon in the atmosphere. I think I controlled burns ever few year rather than hot catastrophic burns will be better for the environment. We need to actively manage the landscape better to sequest more carbon.", "label": 1}, "t113": {"id": "1225386928373030912", "username": "BrettW_online", "date": "2020-02-06 11:53:04+00:00", "text": "Great to have #9Today launching their Bushfire Road to Recovery on Kangaroo Island tomorrow. The crew were on the island today when the CFS were able to declare the Ravine #bushfire grounds safe thanks to the tireless work of our #volunteers . #sagreat #buythemout #shoplocal", "label": 1}, "t114": {"id": "1225383984734990336", "username": "LauraHillsLamb", "date": "2020-02-06 11:41:23+00:00", "text": "B12 deficency leads to brain/nerve damage.", "label": 0}, "t115": {"id": "1225383368281358336", "username": "LauraHillsLamb", "date": "2020-02-06 11:38:56+00:00", "text": "You sound like a well read and intellegent person. What do you mean by \"B12 comes from organic produce in soil\" and how does being in the sun help with B12?", "label": 1}, "t116": {"id": "1225376335566008320", "username": "Jacurtis95", "date": "2020-02-06 11:10:59+00:00", "text": "Isn\u2019t sweeper keeper a position in quidditch?", "label": 0}, "t117": {"id": "1225376185158262785", "username": "Jacurtis95", "date": "2020-02-06 11:10:23+00:00", "text": "Wait I got another one", "label": 0}, "t118": {"id": "1225376041868222464", "username": "Jacurtis95", "date": "2020-02-06 11:09:49+00:00", "text": "Didn\u2019t think they allowed broom sticks on the soccer pitch", "label": 0}, "t119": {"id": "1225375878592360449", "username": "Jacurtis95", "date": "2020-02-06 11:09:10+00:00", "text": "Can tell when someone isn\u2019t online as much as you when you mention you dated someone from twitter and they look at you like you just told them you enjoyed Cats (2019)", "label": 1}, "t120": {"id": "1225374718728916994", "username": "Jacurtis95", "date": "2020-02-06 11:04:33+00:00", "text": "Captain Connor, hey?", "label": 0}, "t121": {"id": "1225374545881653248", "username": "Jacurtis95", "date": "2020-02-06 11:03:52+00:00", "text": "*Neil DeGrasse Tyson voice* earth isn\u2019t forever you moron, you duncehttps://twitter.com/elonmusk/status/1225372729991421953 \u2026", "label": 0}, "t122": {"id": "1225374274648625152", "username": "dendog43", "date": "2020-02-06 11:02:48+00:00", "text": "@MarkSaunders26 thanks for your follow Mark. Cheers from South Australia", "label": 1}, "t123": {"id": "1225374015583219712", "username": "Jacurtis95", "date": "2020-02-06 11:01:46+00:00", "text": "this kind of shit makes me angry enough to type out a lot of words to criticise it but too angry to type anything cohesive enough for those words to be goodhttps://twitter.com/HamishTaylor31/status/1225316948851904512 \u2026", "label": -1}, "t124": {"id": "1225371681545261056", "username": "Jacurtis95", "date": "2020-02-06 10:52:29+00:00", "text": "This one goes out to people complaining about animal crossing like it\u2019s gonna change anything", "label": 0}, "t125": {"id": "1225371677535526912", "username": "Jacurtis95", "date": "2020-02-06 10:52:28+00:00", "text": "I don\u2019t get why people complain about video games that haven\u2019t come out yet - you can just not buy it rather than putting money towards something you already know you\u2019ll complain about", "label": -1}, "t126": {"id": "1225367699758272513", "username": "Jacurtis95", "date": "2020-02-06 10:36:40+00:00", "text": "Especially if Matt starts a Cats discussion youtube channel or podcast", "label": 0}, "t127": {"id": "1225367695870218241", "username": "Jacurtis95", "date": "2020-02-06 10:36:39+00:00", "text": "Slowly but surely I will put money towards each of my mutuals\u2019 creative projects", "label": 1}, "t128": {"id": "1225365610118311936", "username": "Jacurtis95", "date": "2020-02-06 10:28:22+00:00", "text": "Josh is the mime that always seems to hang out with the racist one (iain) so is racist by association", "label": -1}, "t129": {"id": "1225364980771389440", "username": "LauraHillsLamb", "date": "2020-02-06 10:25:52+00:00", "text": "Today found 4 wethers hiding in a mob of ewes. They have a low commercial value as a line of 4 mixed ag wethers but will provide many great meals for my family. I love a bit of mutton.", "label": 1}, "t130": {"id": "1225361227406143488", "username": "LauraHillsLamb", "date": "2020-02-06 10:10:57+00:00", "text": "No worries.", "label": 0}, "t131": {"id": "1225360633283014656", "username": "LauraHillsLamb", "date": "2020-02-06 10:08:35+00:00", "text": "I couldn't afford to eat the meat I do if I had to buy it from a supermarket.", "label": 0}, "t132": {"id": "1225359158611824641", "username": "LauraHillsLamb", "date": "2020-02-06 10:02:44+00:00", "text": "There are a few vegan doctors/guru around promoting the idea that herbivores eat soil to get B12. It's a bit of misinformation that helps them sell idea that humans were/are herbivore if they could eat soil like a cow. Sounds crazy but that's basically what they are saying.", "label": 0}, "t133": {"id": "1225358504208281600", "username": "pointhacks", "date": "2020-02-06 10:00:08+00:00", "text": "TIPS : When is the best time to book flights? [2020] https://phks.co/2S2xsYX #travel #flightbookingpic.twitter.com/Pofd5oHFde", "label": 1}, "t134": {"id": "1225357600482443265", "username": "LauraHillsLamb", "date": "2020-02-06 09:56:32+00:00", "text": "Oysters don't have a brain/CNS.", "label": 0}, "t135": {"id": "1225353679173079040", "username": "LauraHillsLamb", "date": "2020-02-06 09:40:57+00:00", "text": "It doesn't matter if they eat grass on soil or hay or grain. As long as they consume a tiny amount of cobalt they can make b12 via their rumen.", "label": 0}, "t136": {"id": "1225353193061670913", "username": "LauraHillsLamb", "date": "2020-02-06 09:39:01+00:00", "text": "A sheep needs about 200mcg of b12 per day. They don't get it from eating dirty grass. They get it from the gut microbes that they digest which come from their rumen (2nd stomach compartment) .", "label": 0}, "t137": {"id": "1225350815528845313", "username": "LauraHillsLamb", "date": "2020-02-06 09:29:34+00:00", "text": "So you think cows eat soil as dust or mud splatter on the grass?", "label": 0}, "t138": {"id": "1225350126303973376", "username": "James_Jordan", "date": "2020-02-06 09:26:50+00:00", "text": "I suppose it\u2019s that they\u2019re trying to attract punters towards SA markets which is a good thing for us locals!", "label": 1}, "t139": {"id": "1225348670196858885", "username": "LauraHillsLamb", "date": "2020-02-06 09:21:03+00:00", "text": "I don't know of any animal that eats soil to get B12. Which animals are you think of.", "label": 0}, "t140": {"id": "1225345962283085824", "username": "AdrianPAtkinson", "date": "2020-02-06 09:10:17+00:00", "text": "Sparkling Pinot base coming off today as harvest gets underway #PinotNoir @taylorswines #OzV20pic.twitter.com/U9fb67gv4h", "label": 0}, "t141": {"id": "1225344997915910144", "username": "barossagirl72", "date": "2020-02-06 09:06:27+00:00", "text": "Shayne you and Jo need to invent something new that Jo can use in the kitchen or something for the dogs or the sheep and I can help you patent and trademark it. You\u2019ll have your own website in no time!", "label": 0}, "t142": {"id": "1225344825274224640", "username": "LauraHillsLamb", "date": "2020-02-06 09:05:46+00:00", "text": "It would be better to fund the departments that do controlled burns properly so they can coordinate enough prescribed burns to manage the landscape well. I want to burn my thick scrub once or twice a decade but due to limited resources it can't happen until late Autumn, 2021.", "label": 0}, "t143": {"id": "1225343971695554560", "username": "ps2fatboy", "date": "2020-02-06 09:02:23+00:00", "text": "Thank u", "label": 0}, "t144": {"id": "1225343158399062016", "username": "LauraHillsLamb", "date": "2020-02-06 08:59:09+00:00", "text": "NSW has 70K fire fighters and nearly 4000 vehicles. The issue is that these fires were hard to stop. I'm a volunteer fire fighter I would rather spend my time preventing bad fire by lighting good winter fires than fighting summer fires and loosing.", "label": -1}, "t145": {"id": "1225342452434751488", "username": "clinton1550", "date": "2020-02-06 08:56:21+00:00", "text": "And do a good job of ithttps://twitter.com/Charalanahzard/status/1225325782869786625 \u2026", "label": 0}, "t146": {"id": "1225338140908380161", "username": "dendog43", "date": "2020-02-06 08:39:13+00:00", "text": "I just choked on my lobster thermidor @davidmatheson27 @judi_francishttps://twitter.com/PhilHillman1/status/1225336479997546498 \u2026", "label": 0}, "t147": {"id": "1225336210513465344", "username": "collectoffersau", "date": "2020-02-06 08:31:32+00:00", "text": "Seafolly Seafolly - Discount Designer Playsuits For Her From Just AU$99.95: Choose perfectly designed playsuits for making your fashionable look more attractive, so purchase women's designer playsuits now online with a starting price of AU$99.95.", "label": 1}, "t148": {"id": "1225336209280356352", "username": "collectoffersau", "date": "2020-02-06 08:31:32+00:00", "text": "Viator Viator - Sale Book Tours, Activities & Shows In Sydney From Just AU$42: Spend unforgettable holidays in Sydney with exploring the best landmarks, tours & attractions. Book your favourite activities, tours, shows & tickets now online with a starting price of AU$42.", "label": 1}, "t149": {"id": "1225336208261124096", "username": "collectoffersau", "date": "2020-02-06 08:31:32+00:00", "text": "Viator Viator - Sale Book Tours & Activities In Melbourne From Just AU$24: Plan your trip to Melbourne and enjoy the fun of amazing activities, tours, workshops, theme tours & excursions. Pre-book your tickets, tours & activities online with a starting price of AU$24.", "label": 1}, "t150": {"id": "1225322416395579392", "username": "James_Jordan", "date": "2020-02-06 07:36:44+00:00", "text": "Interesting to see Sportsbet betting 119% and 121% in the last two races at Morphettville on Saturday, particularly given the size of the fields. Rest of the market averaging ~129%.", "label": 0}, "t151": {"id": "1225320832152604672", "username": "LastManStands", "date": "2020-02-06 07:30:26+00:00", "text": "Congratulations to the big , Paul Marchesi on achieving LMS Legend status! Cheesy has been the driving force behind Rock Lobsters since his first game in 2011! Since then he's racked up 320 games, 10445 runs, 171 wickets, 97 stumpings and 101 catches! Well done Paul !pic.twitter.com/oZqrhxSR1p", "label": 1}, "t152": {"id": "1225320784694071297", "username": "jeq88", "date": "2020-02-06 07:30:15+00:00", "text": "#selfie #interviewready #wentwell #fingerscrossed #happy #positive #feelingawesome @Port Pirie, South Australia, Australia https://www.instagram.com/p/B8N5PY7H11x0k6DOOBI4KmNtoRUaL7ZxY3zdWw0/?igshid=1gowzeompor6w \u2026", "label": 1}, "t153": {"id": "1225316898327257093", "username": "purealivia", "date": "2020-02-06 07:14:48+00:00", "text": "One more sleep. #shootfilmwelly #believeinfilm #grainisgood #buyfilmnotmegapixelspic.twitter.com/LZT54gsvCj", "label": 0}, "t154": {"id": "1225315706096349184", "username": "ps2fatboy", "date": "2020-02-06 07:10:04+00:00", "text": "https://clips.twitch.tv/YawningSplendidBananaCeilingCat \u2026 These zombie sharks", "label": 0}, "t155": {"id": "1225313190403301376", "username": "pointhacks", "date": "2020-02-06 07:00:04+00:00", "text": "BONUS POINTS : Pick up 500 bonus KrisFlyer miles for each person you refer to join https://phks.co/2BFIa0u pic.twitter.com/HoXEVKVqAQ", "label": 1}, "t156": {"id": "1225312141932019713", "username": "clinton1550", "date": "2020-02-06 06:55:54+00:00", "text": "The system failed to prevent Trump from getting the nomination, it failed to prevent him from becoming President and now it has failed to remove him from office", "label": -1}, "t157": {"id": "1225305167710408704", "username": "BenLeahy12", "date": "2020-02-06 06:28:11+00:00", "text": "Forever thankful for what @wrightcoach12 has done for the @Adelaide36ers organisation. #36ers", "label": 1}, "t158": {"id": "1225303089671884800", "username": "ChakraSarah", "date": "2020-02-06 06:19:56+00:00", "text": "The Australian Federal Government: Finally having our Koalas officially declared Critically Endangered - Sign the Petition! http://chng.it/W6FNbsNC via @ChangeAUS", "label": 0}, "t159": {"id": "1225303071376297984", "username": "Laura_Collins9", "date": "2020-02-06 06:19:51+00:00", "text": "Almost as dusty as when Grizzly visited last time.", "label": 0}, "t160": {"id": "1225302793616936960", "username": "Laura_Collins9", "date": "2020-02-06 06:18:45+00:00", "text": "Always so silly.", "label": 0}, "t161": {"id": "1225301172560392193", "username": "ps2fatboy", "date": "2020-02-06 06:12:19+00:00", "text": "I love it one of the best game so far this year", "label": 1}, "t162": {"id": "1225300749946474497", "username": "Laura_Collins9", "date": "2020-02-06 06:10:38+00:00", "text": "Can I also just clarify I actually did not instruct Archie to sit in the dust. I am a good dog mum.", "label": 0}, "t163": {"id": "1225300664785367041", "username": "Jacurtis95", "date": "2020-02-06 06:10:18+00:00", "text": "I\u2019ve got a really good/gross one for this that I shan\u2019t be posting anywherehttps://twitter.com/Maxquinn/status/1225240895718453248 \u2026", "label": 0}, "t164": {"id": "1225300293232934914", "username": "Laura_Collins9", "date": "2020-02-06 06:08:49+00:00", "text": "This dust in: every day is a good dust storm day. #duststormpic.twitter.com/CNbTM7b8cn", "label": 0}, "t165": {"id": "1225300230633070592", "username": "ps2fatboy", "date": "2020-02-06 06:08:34+00:00", "text": "Love the game been playing it since launch day", "label": 1}, "t166": {"id": "1225298694938877955", "username": "Jacurtis95", "date": "2020-02-06 06:02:28+00:00", "text": "He wears a kimono around the house too", "label": 0}, "t167": {"id": "1225288982755336192", "username": "Leeshalicious_", "date": "2020-02-06 05:23:52+00:00", "text": "What feelings...https://twitter.com/ZodiacFacts/status/1225281830212993024 \u2026", "label": 0}, "t168": {"id": "1225285806815760385", "username": "Jacurtis95", "date": "2020-02-06 05:11:15+00:00", "text": "If we\u2019re being honest pikachu has always been the most annoying part of the pokemon franchise", "label": 0}, "t169": {"id": "1225285735462211585", "username": "listento_lonomy", "date": "2020-02-06 05:10:58+00:00", "text": "I\u2019ve never been able to dump my PC\u2019s out the other end of a rapidly flowing ravine before. It was exhilarating. ...they survived btw. #dnd", "label": 1}, "t170": {"id": "1225280910498549761", "username": "ocky1733", "date": "2020-02-06 04:51:48+00:00", "text": "Poetry in motion", "label": 0}, "t171": {"id": "1225280532130365440", "username": "ocky1733", "date": "2020-02-06 04:50:18+00:00", "text": "How cool is that ?", "label": 0}, "t172": {"id": "1225279299747344385", "username": "FamilyAssn", "date": "2020-02-06 04:45:24+00:00", "text": "Join the AFA: http://family.org.au #strongerfamilies #inspiration #qotd #inspirationalquote #family #children #minds #ideas #creativity #resource #humans #betterfamilies #quote #Disney #WaltDisney #Australiapic.twitter.com/CheEUPKUSt", "label": 1}, "t173": {"id": "1225272337471115264", "username": "DavidEvans_GGL", "date": "2020-02-06 04:17:44+00:00", "text": "Alas, the last of the great characters to play for Australia. Super talented cricketer who debuted at 34 & valued every second he wore the baggy green.", "label": 1}, "t174": {"id": "1225270873831002112", "username": "acton_jus", "date": "2020-02-06 04:11:55+00:00", "text": "Defo", "label": 0}, "t175": {"id": "1225270734039027712", "username": "Leeshalicious_", "date": "2020-02-06 04:11:22+00:00", "text": "Work bitch!pic.twitter.com/Yqh3lbWHPw", "label": 0}, "t176": {"id": "1225270679718641665", "username": "DavidEvans_GGL", "date": "2020-02-06 04:11:09+00:00", "text": "The older we get, the faster we were. Still looks to be hitting them ok.https://twitter.com/RickyPonting/status/1225266059277586432 \u2026", "label": 0}, "t177": {"id": "1225270617399689218", "username": "Jacurtis95", "date": "2020-02-06 04:10:54+00:00", "text": "Election by a Port Lincoln style tuna throwing competition", "label": 0}, "t178": {"id": "1225269450305232898", "username": "Jacurtis95", "date": "2020-02-06 04:06:16+00:00", "text": "Getting a call from interstate on Line 5 of the studio phone: this is Telstra, we notice that your internet connection is being used by hackers - are you in charge of the internet connection there? Me: can you confirm my address please? Caller: ok then *hangs up*", "label": 1}, "t179": {"id": "1225267639347343366", "username": "wcsentinel", "date": "2020-02-06 03:59:04+00:00", "text": "More than 240 GoFundMe pages raise $3.8 million for Kangaroo Island bushfire recovery http://www.westcoastsentinel.com.au/story/6615003/more-than-240-gofundme-pages-raise-38-million-for-kangaroo-island-bushfire-recovery/?src=rss \u2026pic.twitter.com/afSNpGNTpP", "label": 0}, "t180": {"id": "1225267633173352448", "username": "wcsentinel", "date": "2020-02-06 03:59:02+00:00", "text": "Drink driving blitz targets regions http://www.westcoastsentinel.com.au/story/6617545/drink-driving-blitz-targets-regions/?src=rss \u2026pic.twitter.com/bQPAZpahaY", "label": 0}, "t181": {"id": "1225267407825989632", "username": "DavidEvans_GGL", "date": "2020-02-06 03:58:09+00:00", "text": "44 days apparently.", "label": 0}, "t182": {"id": "1225267012126957569", "username": "EyreTribune", "date": "2020-02-06 03:56:34+00:00", "text": "3D aerial maps to help fire ground recovery on Kangaroo Island http://www.eyretribune.com.au/story/6617994/3d-aerial-maps-to-help-fire-ground-recovery-on-kangaroo-island/?src=rss \u2026pic.twitter.com/qtY6lTN2BR", "label": 0}, "t183": {"id": "1225267007760678912", "username": "EyreTribune", "date": "2020-02-06 03:56:33+00:00", "text": "Innovative new Indigenous inspired cruises to hit the Coorong http://www.eyretribune.com.au/story/6617300/innovative-new-indigenous-inspired-cruises-to-hit-the-coorong/?src=rss \u2026pic.twitter.com/R7NrG4qUXY", "label": 1}, "t184": {"id": "1225267004518457345", "username": "EyreTribune", "date": "2020-02-06 03:56:32+00:00", "text": "More than 240 GoFundMe pages raise $3.8 million for Kangaroo Island bushfire recovery http://www.eyretribune.com.au/story/6615003/more-than-240-gofundme-pages-raise-38-million-for-kangaroo-island-bushfire-recovery/?src=rss \u2026pic.twitter.com/kMzgLLocfS", "label": 0}, "t185": {"id": "1225266787303903233", "username": "kjrussell34", "date": "2020-02-06 03:55:41+00:00", "text": "I remember he always spoke highly of the @pioneers_ball at the after game function.", "label": 0}, "t186": {"id": "1225266385493749762", "username": "kjrussell34", "date": "2020-02-06 03:54:05+00:00", "text": "So sad mate", "label": -1}, "t187": {"id": "1225264734095560705", "username": "JOXSports", "date": "2020-02-06 03:47:31+00:00", "text": "That's how to start your Career! @HaleyMoore_20 fires 7 under 66 in R1 @VicOpenGolf #WomensGolf #BearDownpic.twitter.com/zKgjuHn5Wo", "label": 0}, "t188": {"id": "1225261945982291968", "username": "oz_farmer_nerd", "date": "2020-02-06 03:36:26+00:00", "text": "The picture on the cover of this booklet makes me feel physically ill. Who would do that?!pic.twitter.com/qWDTqK59in", "label": 0}, "t189": {"id": "1225250135942168576", "username": "Jacurtis95", "date": "2020-02-06 02:49:31+00:00", "text": "Isn\u2019t Grom older?", "label": 0}, "t190": {"id": "1225249209466515462", "username": "DavidEvans_GGL", "date": "2020-02-06 02:45:50+00:00", "text": "Shouldn\u2019t you wait til it\u2019s 43C with a hot northerly?", "label": 0}, "t191": {"id": "1225249025814777858", "username": "ocky1733", "date": "2020-02-06 02:45:06+00:00", "text": "Big loss", "label": 0}, "t192": {"id": "1225247873425530880", "username": "ps2fatboy", "date": "2020-02-06 02:40:31+00:00", "text": "Dude amazing congrats", "label": 1}, "t193": {"id": "1225247595926183936", "username": "ps2fatboy", "date": "2020-02-06 02:39:25+00:00", "text": "Lovin' #ZombieArmy4 #ZombieArmy4DeadWar #twitchtv Be on again to end the zombies With co op crew This is the best zombie game I've played in ages super fun @zombiearmy @Rebellion Nut shot zombie fun pic.twitter.com/01VzIP7aeN", "label": 1}, "t194": {"id": "1225240981903151105", "username": "same_weather", "date": "2020-02-06 02:13:08+00:00", "text": "Orientos Airport, Australia - Pakuba Airfield, Uganda OXO-PAF Weather (Fri): clear-day/28\u00b0C", "label": 0}, "t195": {"id": "1225240637882028032", "username": "busanfan", "date": "2020-02-06 02:11:46+00:00", "text": "Anyone using a Google assistant?", "label": 0}, "t196": {"id": "1225239048060456960", "username": "JeamesG", "date": "2020-02-06 02:05:27+00:00", "text": "Hello @danielhowell & @AmazingPhil are you restocking this item? as I have saved up enough to buy it but I can\u2019t find it on your shop?pic.twitter.com/Eb99M7OBrZ", "label": 0}, "t197": {"id": "1225234183183716352", "username": "Jacurtis95", "date": "2020-02-06 01:46:07+00:00", "text": "Can\u2019t believe Buttegeig not only rigged the vote but also finds Grom more attractive than you", "label": 1}, "t198": {"id": "1225232886648860672", "username": "SMikic13", "date": "2020-02-06 01:40:58+00:00", "text": "Picturesque in the summer time and even better during winter", "label": 1}, "t199": {"id": "1225231987222302720", "username": "MattJelonek", "date": "2020-02-06 01:37:24+00:00", "text": "Captured my fourth #WRC #RallyeMonteCarlo only two weeks ago. A quick look back at the best that came from it with @McKlein_Rally https://twitter.com/McKlein_Rally/status/1222504782826496000 \u2026", "label": 1}, "t200": {"id": "1225231784696172544", "username": "DavidEvans_GGL", "date": "2020-02-06 01:36:35+00:00", "text": "Same for working dogs.", "label": 0}, "t201": {"id": "1225231171350458369", "username": "Jippas", "date": "2020-02-06 01:34:09+00:00", "text": "Let\u2019s go @Adelaide_FC !!! #WeFlyAsOne https://twitter.com/Adelaide_FC/status/1224973433873694720 \u2026pic.twitter.com/uwnYdkEjBz", "label": 0}, "t202": {"id": "1225226648598937601", "username": "samcwillis", "date": "2020-02-06 01:16:11+00:00", "text": "Not age 5. Maybe age 21. Otherwise I\u2019d rather learn everything now.", "label": 0}, "t203": {"id": "1225225024543444994", "username": "Jacurtis95", "date": "2020-02-06 01:09:44+00:00", "text": "I will say that the show is on valentine\u2019s day so either gonna have an interesting first date if I... ya know... get onehttps://twitter.com/Jacurtis95/status/1225222254402797569 \u2026", "label": 0}, "t204": {"id": "1225223174951854082", "username": "Jacurtis95", "date": "2020-02-06 01:02:23+00:00", "text": "I\u2019ll kiss my granddaughter, I\u2019ll kiss your granddaughter, I\u2019ll kiss everyone\u2019s granddaughters! I dontgive fuk!", "label": 1}, "t205": {"id": "1225222758742708224", "username": "Jacurtis95", "date": "2020-02-06 01:00:43+00:00", "text": "Hey... nicehttps://twitter.com/OmegaUGround/status/1225182589553651713 \u2026", "label": 0}, "t206": {"id": "1225222584549068801", "username": "Jacurtis95", "date": "2020-02-06 01:00:02+00:00", "text": "Early exist poll canvassing I did indicated a fair lead in favour of myself though", "label": 1}, "t207": {"id": "1225222331502477312", "username": "wcsentinel", "date": "2020-02-06 00:59:02+00:00", "text": "Drink-driver caught at Ceduna http://www.westcoastsentinel.com.au/story/6616983/drink-driver-caught-at-ceduna/?src=rss \u2026pic.twitter.com/eVKShu2CJn", "label": 0}, "t208": {"id": "1225222254402797569", "username": "Jacurtis95", "date": "2020-02-06 00:58:43+00:00", "text": "Just got myself free tickets to Tim Ferguson\u2019s fringe show", "label": 1}, "t209": {"id": "1225219655922356225", "username": "acton_jus", "date": "2020-02-06 00:48:24+00:00", "text": "But when you walked away the picture went fuzzy! How were we supposed to watch Grange hill like that!", "label": 1}, "t210": {"id": "1225216633704042496", "username": "Fallon_84", "date": "2020-02-06 00:36:23+00:00", "text": "Retweet to read later. I recently read Dare to Lead and found it very beneficial readinghttps://twitter.com/lyndelleg/status/1225152140424826882 \u2026", "label": 0}, "t211": {"id": "1225213905229750272", "username": "PIGSZY", "date": "2020-02-06 00:25:33+00:00", "text": "What A Turkey Over An Hour Early To Chiro ! #brainbroken #whoami @South Australia https://www.instagram.com/p/B8NIolfDH6A/?igshid=15qh9ln1frtmw \u2026", "label": 0}, "t212": {"id": "1225211581702651904", "username": "Jacurtis95", "date": "2020-02-06 00:16:19+00:00", "text": "Can\u2019t defame the dead, baby", "label": -1}, "t213": {"id": "1225211335262101505", "username": "Jacurtis95", "date": "2020-02-06 00:15:20+00:00", "text": "Wasn\u2019t Kirk Douglas a piece of shit? Pretty sure I saw stuff about him being a piece of shit 103 years is a long time to be a piece of shit, you\u2019d think he\u2019d have figured that out before he kicked it", "label": -1}, "t214": {"id": "1225209708971085826", "username": "Jacurtis95", "date": "2020-02-06 00:08:52+00:00", "text": "For me I\u2019ve come to accept I can either be happy with a relationship or happy with work, and not really both at the same time If work goes to shit I\u2019ll know I\u2019m days away from finding love", "label": 1}}