{"t0": {"id": "1250574101355216896", "username": "weXploretravel", "date": "2020-04-15 23:57:54+00:00", "text": "James Clement let go from Freo to the Pies. Did very well at Collingwood.", "label": 0}, "t1": {"id": "1250572188966514689", "username": "PeroNasteski", "date": "2020-04-15 23:50:19+00:00", "text": "Poor old Gladys gets stage fright when the preacher is aroundhttps://twitter.com/vanOnselenP/status/1250553888907780098 \u2026", "label": -1}, "t2": {"id": "1250569050192670721", "username": "tols03", "date": "2020-04-15 23:37:50+00:00", "text": "Ugh man is it sad that I don't want her to play meghttps://twitter.com/ArianaGrande/status/1250545364018462720 \u2026", "label": -1}, "t3": {"id": "1250568140024696833", "username": "cq_rescue", "date": "2020-04-15 23:34:13+00:00", "text": "#RACQ #CQRescue flew to Long Island in the Whitsundays last night to transfer an unwell man to Mackay Base Hospital.pic.twitter.com/uyG6i2mtts", "label": 0}, "t4": {"id": "1250566550806949888", "username": "tols03", "date": "2020-04-15 23:27:54+00:00", "text": "This is no time for diplomacy https://twitter.com/vai1ima/status/1250485131476742144 \u2026", "label": 0}, "t5": {"id": "1250566333395120128", "username": "downunderguy2", "date": "2020-04-15 23:27:02+00:00", "text": "Wow, you have a population of almost 330,000,000, so you have tested just 1% of the people. Great work!!!!", "label": 1}, "t6": {"id": "1250563075238838272", "username": "downunderguy2", "date": "2020-04-15 23:14:06+00:00", "text": "Wow, that didn\u2019t take long - only 3 months to get your act together.", "label": 1}, "t7": {"id": "1250562528020533248", "username": "Licy_be", "date": "2020-04-15 23:11:55+00:00", "text": "Supporting Female CHH & Pop Playlist on Spotify @OMGitsWande @Vrosemusic @AngieRoseMusikhttps://open.spotify.com/user/22qmj6cqysmhdwiv2n3sxztyy/playlist/7Kb0EkVxb1fb1bEIha9cVc?si=uAMcnE-3QRGuS2xo6HcdSA \u2026", "label": 0}, "t8": {"id": "1250560670367510528", "username": "CreaseyJack", "date": "2020-04-15 23:04:32+00:00", "text": "Aus bushfire season starts today", "label": 0}, "t9": {"id": "1250559060543340544", "username": "Mitch84726581", "date": "2020-04-15 22:58:08+00:00", "text": "Australia was the first country to shut down flights, specifically from China. A very unpopular move at the time. We went against WHO advice. They were telling us not to shut down flights. Then stupid Australians got on cruise ships even though they knew about the virus.", "label": -1}, "t10": {"id": "1250557767712038914", "username": "GoodremFan", "date": "2020-04-15 22:53:00+00:00", "text": "Never", "label": 0}, "t11": {"id": "1250557630084313088", "username": "Mitch84726581", "date": "2020-04-15 22:52:27+00:00", "text": "Just in case you didn't notice ... Australia has one of the lowest death rates in the world. Notice the police are involved with the cruise ships. They doctored their information. In addition, who knew if the gov could be sued if they shut down an internat shipping company.", "label": -1}, "t12": {"id": "1250557185299365889", "username": "PeteOnTweet1", "date": "2020-04-15 22:50:41+00:00", "text": "Clever dogs! https://giphy.com/gifs/smart-doggo-RLhVSyEj2GFVXDZVqy?utm_source=media-link&utm_medium=landing&utm_campaign=Media%20Links&utm_term= \u2026", "label": 1}, "t13": {"id": "1250552781183660032", "username": "Cathrinmachin", "date": "2020-04-15 22:33:11+00:00", "text": "Oh my goodness are you referring to that series on Netflix? I can\u2019t remember the name but oh my goodness it was such an amazing episode", "label": 1}, "t14": {"id": "1250552213232955393", "username": "Cathrinmachin", "date": "2020-04-15 22:30:56+00:00", "text": "This is my painting of the Cats eye nebula. It has to be one of my absolute favourites I\u2019ve ever made. I\u2019ve recently realised that lots of people are reposting this without credit. I spent so much time and care (and money on materials) making it as beautifully as I could.pic.twitter.com/409rmQi6p9", "label": 1}, "t15": {"id": "1250551789671157760", "username": "chlosmith_99", "date": "2020-04-15 22:29:15+00:00", "text": "The only reason I wake up these days is to see nialls mirror selfie video things", "label": 0}, "t16": {"id": "1250549190263844865", "username": "crissyleebates", "date": "2020-04-15 22:18:55+00:00", "text": "Omggg it feels like it\u2019s been forever https://twitter.com/toricummingsxxx/status/1250538499297562624 \u2026", "label": 0}, "t17": {"id": "1250544426792837121", "username": "Chargey76", "date": "2020-04-15 21:59:59+00:00", "text": "Even overcast & drizzly it\u2019s still a magic part of the world & a great pit stop on the way to Cairns for Races today! Cardwell pic.twitter.com/ArLOSFwdQJ", "label": 0}, "t18": {"id": "1250543629837295616", "username": "downunderguy2", "date": "2020-04-15 21:56:49+00:00", "text": "If, as you claim, Bolton \u2018completely debunked\u2019 the statement, how do you explain America being so easily top of this list?pic.twitter.com/2G8O6rwTf7", "label": 1}, "t19": {"id": "1250538410139250688", "username": "janzey_pratt", "date": "2020-04-15 21:36:05+00:00", "text": "Health workers are being told to re use masks gowns and gloves. Not good for our frontline workers", "label": 0}, "t20": {"id": "1250532354319249408", "username": "Hatfitzcara", "date": "2020-04-15 21:12:01+00:00", "text": "Thank you so much @rootsandfusion appreciate you airing our song this piece is actually about having high anxiety and trying to let go of that possibly apt in timing https://twitter.com/rootsandfusion/status/1250519616226504704 \u2026", "label": 1}, "t21": {"id": "1250511424440291329", "username": "shanebuderim", "date": "2020-04-15 19:48:51+00:00", "text": "@RadioTABAus if we\u2019re picking base ballers it\u2019s Derek Jeter for me!", "label": 0}, "t22": {"id": "1250506513245970432", "username": "BPEarth", "date": "2020-04-15 19:29:20+00:00", "text": "#33008 Einasleigh QLD 4871, Australia map: https://www.google.com/maps/place/-18.9809008947,144.226917309/data=!3m1!1e3!4m2!3m1!1s0x0:0x0 \u2026pic.twitter.com/UAnH2SVi2P", "label": 0}, "t23": {"id": "1250503344948252672", "username": "RobynMay53", "date": "2020-04-15 19:16:45+00:00", "text": "Gold!https://twitter.com/firstdogonmoon/status/1250326118822866948 \u2026", "label": 0}, "t24": {"id": "1250500545439133696", "username": "shanebuderim", "date": "2020-04-15 19:05:37+00:00", "text": "@RadioTABAus it would have to be Kelly Slater, I love the sound of an endless summer and be at the top of my sport for so long. In my downtime I don\u2019t mind a game of golf and I\u2019m real good at that as well. Sounds like a hard life.", "label": 1}, "t25": {"id": "1250499830742265856", "username": "Mitch84726581", "date": "2020-04-15 19:02:47+00:00", "text": "You shouldn't have paid illegally for a boat in the first place ..... after paying for a plane trip.", "label": 0}, "t26": {"id": "1250498797769089024", "username": "fcukeveryname", "date": "2020-04-15 18:58:41+00:00", "text": "fuck solberg", "label": -1}, "t27": {"id": "1250498300991553537", "username": "Mitch84726581", "date": "2020-04-15 18:56:42+00:00", "text": "What rot. They can go home any time they like. They haven't been found tobe realrefugees which is why they're still being held. You havebeen sucked in.", "label": 0}, "t28": {"id": "1250497386188660736", "username": "Mitch84726581", "date": "2020-04-15 18:53:04+00:00", "text": "They're in isolation. If they practice good hygiene they have less chance of getting covid than most others. Be quiet. We have important things to do and fix. A bunch of single men who selishly left their family and friends is not on that list.", "label": 1}, "t29": {"id": "1250496707067932674", "username": "Mitch84726581", "date": "2020-04-15 18:50:22+00:00", "text": "They can't prove that without reasonable doubt either.", "label": 0}, "t30": {"id": "1250496541694980096", "username": "Mitch84726581", "date": "2020-04-15 18:49:43+00:00", "text": "Possibly, Imogen has it right. Maybe you should listen to yourself.", "label": 0}, "t31": {"id": "1250496236647354368", "username": "Mitch84726581", "date": "2020-04-15 18:48:30+00:00", "text": "Yeah. I don't know of you've noticed but we're in the middle of a Pandemic. The entire world is shut down and money had to be spent on supporting the economy. Truly unprecedented times. Grow up.", "label": 1}, "t32": {"id": "1250491587395760129", "username": "lifeadvicebotto", "date": "2020-04-15 18:30:02+00:00", "text": "He'll have nauseous for a few hours, then he'll be fine.", "label": 0}, "t33": {"id": "1250486488967442433", "username": "valbailub", "date": "2020-04-15 18:09:46+00:00", "text": "I'd like to know if Morrison et al will be onto it. I'm with you Eddy,", "label": 0}, "t34": {"id": "1250465802991460352", "username": "valbailub", "date": "2020-04-15 16:47:34+00:00", "text": "He's a bot! Following 7 journalists and apparently 0 followers last check. They're out and about right now.", "label": 0}, "t35": {"id": "1250464046022709248", "username": "valbailub", "date": "2020-04-15 16:40:35+00:00", "text": "Thank you", "label": 0}, "t36": {"id": "1250462282330456065", "username": "Sarahlina84", "date": "2020-04-15 16:33:35+00:00", "text": "You can imagine why my husband, who\u2019s a Teaching Principal lost it when he saw this https://twitter.com/theprojecttv/status/1250378329531744262 \u2026", "label": 0}, "t37": {"id": "1250458990816841728", "username": "PeroNasteski", "date": "2020-04-15 16:20:30+00:00", "text": "Fucken typical ,our kids are lambs to the slaughterhttps://twitter.com/DavidGr07837209/status/1250419945424343040 \u2026", "label": 0}, "t38": {"id": "1250456162593427458", "username": "PeroNasteski", "date": "2020-04-15 16:09:16+00:00", "text": "Like Morrison a blatant bulshit artisthttps://twitter.com/TonyHWindsor/status/1250181509916405761 \u2026", "label": 0}, "t39": {"id": "1250455401595723776", "username": "PeroNasteski", "date": "2020-04-15 16:06:14+00:00", "text": "I\u2019m not sending my kids to school in them middle of a pandemichttps://twitter.com/MikeCarlton01/status/1250287509986086914 \u2026", "label": 0}, "t40": {"id": "1250450914839650304", "username": "toittttt_", "date": "2020-04-15 15:48:25+00:00", "text": "Dumbledore wouldn\u2019t let this happen #COVID19", "label": 0}, "t41": {"id": "1250445640791764992", "username": "toittttt_", "date": "2020-04-15 15:27:27+00:00", "text": "Send it to meeeee", "label": 0}, "t42": {"id": "1250437998107230208", "username": "PeteOnTweet1", "date": "2020-04-15 14:57:05+00:00", "text": "Yes, exactly! It is what it is. Thankfully the technology of our modern world allows for virtual connections via the interwebs when real face-to-face presence isn't an option... not the best but until then, we make it work! Gotta do what we can to keep the country running, eh", "label": 0}, "t43": {"id": "1250432479967580166", "username": "Static7s", "date": "2020-04-15 14:35:09+00:00", "text": "Please take my mind off this tonight", "label": 0}, "t44": {"id": "1250432152438620163", "username": "Static7s", "date": "2020-04-15 14:33:51+00:00", "text": "Thanks muchael. Sorry x when Does your time off start?", "label": 0}, "t45": {"id": "1250431813064912897", "username": "Static7s", "date": "2020-04-15 14:32:30+00:00", "text": "I haven\u2019t locked my front door I need to oh gosh", "label": 0}, "t46": {"id": "1250431580377513987", "username": "Static7s", "date": "2020-04-15 14:31:35+00:00", "text": "No because it\u2019s literally made me freeze not move around do anything, I haven\u2019t slept x since the night before last. Done any work. I\u2019m drowning. Suggest anything please?", "label": 0}, "t47": {"id": "1250428885839142913", "username": "Static7s", "date": "2020-04-15 14:20:52+00:00", "text": "What sorry I won\u2019t do it. I don\u2019t know what though, I was being serious but I\u2019ll stop.", "label": 0}, "t48": {"id": "1250428594842513411", "username": "Static7s", "date": "2020-04-15 14:19:43+00:00", "text": "What is yh?", "label": 0}, "t49": {"id": "1250428432648830976", "username": "Static7s", "date": "2020-04-15 14:19:04+00:00", "text": "Out again.https://twitter.com/420iloveweed/status/1250056255416254465 \u2026", "label": 0}, "t50": {"id": "1250428124606550018", "username": "Static7s", "date": "2020-04-15 14:17:51+00:00", "text": "you\u2019re so beautiful come here baby", "label": 1}, "t51": {"id": "1250427696179376128", "username": "downunderguy2", "date": "2020-04-15 14:16:09+00:00", "text": "That changes when a state of emergency is declared.https://www.google.com.au/amp/s/www.businessinsider.com/california-washington-state-of-emergency-coronavirus-what-it-means-2020-3%3famp \u2026", "label": 0}, "t52": {"id": "1250427518110142473", "username": "Static7s", "date": "2020-04-15 14:15:26+00:00", "text": "Yeah same", "label": 0}, "t53": {"id": "1250427438942707713", "username": "Static7s", "date": "2020-04-15 14:15:07+00:00", "text": "You there love?", "label": 1}, "t54": {"id": "1250427281215868934", "username": "Static7s", "date": "2020-04-15 14:14:30+00:00", "text": "Sapiosexual", "label": 0}, "t55": {"id": "1250427177243308042", "username": "Static7s", "date": "2020-04-15 14:14:05+00:00", "text": "Being filmed", "label": 0}, "t56": {"id": "1250426737810231302", "username": "Static7s", "date": "2020-04-15 14:12:20+00:00", "text": "Omg are you kidding I cant believe you! Ok first time ever just now and yesterday. It\u2019s frozen me, I need to perform. I\u2019m freaking the fuck out", "label": -1}, "t57": {"id": "1250426428237033473", "username": "Static7s", "date": "2020-04-15 14:11:06+00:00", "text": "Hi beautiful hope you\u2019re well", "label": 1}, "t58": {"id": "1250426154806210560", "username": "Static7s", "date": "2020-04-15 14:10:01+00:00", "text": "It\u2019s boring af", "label": 0}, "t59": {"id": "1250426111168675840", "username": "downunderguy2", "date": "2020-04-15 14:09:51+00:00", "text": "No surprise there....pic.twitter.com/VeRBGdnjNc", "label": 0}, "t60": {"id": "1250425670326312960", "username": "Static7s", "date": "2020-04-15 14:08:06+00:00", "text": "@bra_segun Michael someone just told me that China admitted to bio terrorism but then started ranting. Has anything like that actually happened admitting?", "label": 0}, "t61": {"id": "1250425405502181376", "username": "downunderguy2", "date": "2020-04-15 14:07:03+00:00", "text": "A bit dated, but not just an American problem...pic.twitter.com/BJU8XRd4Wr", "label": 0}, "t62": {"id": "1250424778227191809", "username": "Static7s", "date": "2020-04-15 14:04:33+00:00", "text": "@Jay1972Jay are you here?", "label": 0}, "t63": {"id": "1250424282137550850", "username": "downunderguy2", "date": "2020-04-15 14:02:35+00:00", "text": "Shouldn\u2019t that be motherfuquers? (We have cheques too!)", "label": 0}, "t64": {"id": "1250420038353309697", "username": "Robertjohnklin2", "date": "2020-04-15 13:45:43+00:00", "text": "Fuck right off,the people are going to stick that vaccine right in your eye.https://twitter.com/BillGates/status/1250292126643941376 \u2026", "label": -1}, "t65": {"id": "1250413795500888066", "username": "javmunozh", "date": "2020-04-15 13:20:55+00:00", "text": "promiscuous girl, wherever u are, I\u2019m all alone and it\u2019s u that i wanttt", "label": 0}, "t66": {"id": "1250412566825730055", "username": "downunderguy2", "date": "2020-04-15 13:16:02+00:00", "text": "That would be me.....pic.twitter.com/VElYw2JTLY", "label": 0}, "t67": {"id": "1250411956273434624", "username": "Static7s", "date": "2020-04-15 13:13:36+00:00", "text": "Course you do. Are you ok?", "label": 0}, "t68": {"id": "1250411727679709186", "username": "Static7s", "date": "2020-04-15 13:12:42+00:00", "text": "My shoulders started to shake. Definite yes. Holding myself back I need to finish it.", "label": 0}, "t69": {"id": "1250411600843911168", "username": "infinitexrauhl", "date": "2020-04-15 13:12:11+00:00", "text": "jb, Ansel elgort, Cody Simpson", "label": 0}, "t70": {"id": "1250410959719378944", "username": "Static7s", "date": "2020-04-15 13:09:38+00:00", "text": "So welcome thank you", "label": 1}, "t71": {"id": "1250410631884189696", "username": "javmunozh", "date": "2020-04-15 13:08:20+00:00", "text": "I\u2019ll keep saying those things then", "label": 0}, "t72": {"id": "1250404914712346624", "username": "Bel52958381", "date": "2020-04-15 12:45:37+00:00", "text": "I don\u2019t think I have yellow pansies, I\u2019ll check tomoz. They aren\u2019t in my pansy patch but I do have a yellow patch they might be growing in lol. I think I need to make a list also! Great idea!", "label": 1}, "t73": {"id": "1250403605552623616", "username": "Lyall", "date": "2020-04-15 12:40:25+00:00", "text": "I\u2019m going to look at the ingredient lists of the enteral feeds we use in the ICU at work tomorrow @FatEmperor @DrPaulMason", "label": 0}, "t74": {"id": "1250401986672881671", "username": "Lyall", "date": "2020-04-15 12:33:59+00:00", "text": "Fascinating Discussion on Avoiding Viral Impacts of #covid19 with @DrPaulMason Mason https://youtu.be/BkUdD8odrdc on the @FatEmperor Podcast", "label": 0}, "t75": {"id": "1250401132200882177", "username": "toittttt_", "date": "2020-04-15 12:30:35+00:00", "text": "Okay real talk @theprojecttv #TheProject @abcnews #abcnewspic.twitter.com/PVNmUfaOcA", "label": 0}, "t76": {"id": "1250398088096698368", "username": "javmunozh", "date": "2020-04-15 12:18:30+00:00", "text": "Waitin for ya", "label": 0}, "t77": {"id": "1250397120244244480", "username": "Jake18051", "date": "2020-04-15 12:14:39+00:00", "text": "A older picture but still a TF and again art by @IndustriesKieli \u201cLooks like I\u2019m a werevixen\u201d #TFTuesdaypic.twitter.com/jzH3BUGSwB", "label": 1}, "t78": {"id": "1250394244172283909", "username": "Phantom_Knight8", "date": "2020-04-15 12:03:13+00:00", "text": "People might be wondering on why I haven\u2019t renewed my Pinned yet I think. Well the reason why is because the artist I go to is doing a couple more pictures for me (that will be in like a comic book page look) so please do be patient with that.", "label": 1}, "t79": {"id": "1250393012745564161", "username": "Dinachi7", "date": "2020-04-15 11:58:20+00:00", "text": "Still one of my favourite videospic.twitter.com/E126taFgND", "label": 0}, "t80": {"id": "1250392926108168192", "username": "diotaema", "date": "2020-04-15 11:57:59+00:00", "text": "get ready to rumble", "label": 0}, "t81": {"id": "1250389002374369280", "username": "barrymo17885962", "date": "2020-04-15 11:42:23+00:00", "text": "Simply friends hi everybody I\u2019ve been away for a bit now this virus is with us gives me the time to practise some new songs Grenada ghost riders your my world it\u2019s now or never Mississippi when your smiling moon river and others Playing Sunday\u2019s soon", "label": 1}, "t82": {"id": "1250384999510970371", "username": "Tonic_Lust", "date": "2020-04-15 11:26:29+00:00", "text": "Should have a Sleepover at mine asap! I will curl your hair for you! I'm really good at it!", "label": 1}, "t83": {"id": "1250383683355201537", "username": "MrLeonWilson", "date": "2020-04-15 11:21:15+00:00", "text": "Too right, Karen, if we're going to be isolated for months I'd suggest dry season here is a pretty solid option!", "label": 0}, "t84": {"id": "1250382708087255043", "username": "lotzhobbitfeet", "date": "2020-04-15 11:17:23+00:00", "text": "Basis for the 204 Ruger....", "label": 0}, "t85": {"id": "1250380293430579200", "username": "Mako_Ozzz", "date": "2020-04-15 11:07:47+00:00", "text": "will covid-19 last", "label": 0}, "t86": {"id": "1250376853648330754", "username": "OutbackSanta", "date": "2020-04-15 10:54:07+00:00", "text": "Lol I keep phone screen shots too , but then forget why I saved them", "label": 1}, "t87": {"id": "1250376654205022213", "username": "Tonic_Lust", "date": "2020-04-15 10:53:19+00:00", "text": "I've been eating alot of pancakes for dinner lol", "label": 0}, "t88": {"id": "1250375131030933505", "username": "lotzhobbitfeet", "date": "2020-04-15 10:47:16+00:00", "text": "End of row coming up!", "label": 0}, "t89": {"id": "1250374889564827649", "username": "lotzhobbitfeet", "date": "2020-04-15 10:46:19+00:00", "text": "Either a faulty WAS or more likely a connection issue.....", "label": 0}, "t90": {"id": "1250374028126064641", "username": "downunderguy2", "date": "2020-04-15 10:42:53+00:00", "text": "That is my winter outfit...", "label": 0}, "t91": {"id": "1250373991404957696", "username": "KarlTims", "date": "2020-04-15 10:42:45+00:00", "text": "The best ever Generational culture that will live on", "label": 1}, "t92": {"id": "1250373730724753408", "username": "Cathrinmachin", "date": "2020-04-15 10:41:42+00:00", "text": "Well I mean he followed me but I actually didn\u2019t know who the heck he was. but anyway definitely blocked and reported at this point", "label": 0}, "t93": {"id": "1250373615033266177", "username": "downunderguy2", "date": "2020-04-15 10:41:15+00:00", "text": "Not really that cold, that is 65F. We dont have dedicated heating in our house, just reverse cycle air conditioning.", "label": 0}, "t94": {"id": "1250373536494931969", "username": "KevinPe68465598", "date": "2020-04-15 10:40:56+00:00", "text": "how soon do you know of any systems,of coroner virus.", "label": 0}, "t95": {"id": "1250373442911662081", "username": "Cathrinmachin", "date": "2020-04-15 10:40:34+00:00", "text": "Ooooooh now that\u2019s an idea I love", "label": 1}, "t96": {"id": "1250372968305160192", "username": "PetehugauH", "date": "2020-04-15 10:38:41+00:00", "text": "Why would you entertain him ?https://twitter.com/leighsales/status/1250328952813391872 \u2026", "label": 0}, "t97": {"id": "1250369187056209920", "username": "PeroNasteski", "date": "2020-04-15 10:23:39+00:00", "text": "Morrison makes these draconian rules and expects people to listen to him ,he really has his head in the clouds ,I\u2019m not letting my kids go to school in the middle of a pandemichttps://twitter.com/vanOnselenP/status/1250169289224507392 \u2026", "label": 0}, "t98": {"id": "1250369090901827585", "username": "downunderguy2", "date": "2020-04-15 10:23:16+00:00", "text": "Correct, we were laughing out loud when trump said Coronavirus would disappear when it got warm. We just had the hottest summer on record. We still have the virus.pic.twitter.com/np1VIvD0wf", "label": 0}, "t99": {"id": "1250368227181383680", "username": "weXploretravel", "date": "2020-04-15 10:19:50+00:00", "text": "Come to think of it, if the ol triple plugger is on the menu you probably would get a feed on a remote bit of coastline.", "label": 0}, "t100": {"id": "1250368127533076482", "username": "downunderguy2", "date": "2020-04-15 10:19:26+00:00", "text": "Autumn now, winter in 6 weeks. Temperatures will probably drop to about 18C during the day in winter.", "label": 0}, "t101": {"id": "1250367487369072641", "username": "PetehugauH", "date": "2020-04-15 10:16:54+00:00", "text": "@vanOnselenP do you still believe that 35,000 to 100,000 will die in Australia as per your comments last month ?", "label": -1}, "t102": {"id": "1250367256376119296", "username": "PeroNasteski", "date": "2020-04-15 10:15:59+00:00", "text": "What about his kids being taken out of school whilst advocating other kids attend school ,definitely not leading by examplehttps://twitter.com/EddyJokovich/status/1250301117474295809 \u2026", "label": 0}, "t103": {"id": "1250367066638409730", "username": "downunderguy2", "date": "2020-04-15 10:15:14+00:00", "text": "Well into Autumn here...(temps are C)pic.twitter.com/AxQGIpsvxG", "label": 0}, "t104": {"id": "1250365974965964801", "username": "weXploretravel", "date": "2020-04-15 10:10:53+00:00", "text": "There you go, price for special entry visa has been set.", "label": 0}, "t105": {"id": "1250365641724276740", "username": "weXploretravel", "date": "2020-04-15 10:09:34+00:00", "text": "The triple plugger, yum!", "label": 0}, "t106": {"id": "1250364070932316161", "username": "downunderguy2", "date": "2020-04-15 10:03:19+00:00", "text": "I reported it.", "label": 0}, "t107": {"id": "1250356348107149313", "username": "weXploretravel", "date": "2020-04-15 09:32:38+00:00", "text": "That's a very generous breakup of the state, considering Heavey Bay is almost a suburb of the Sunshine Coast. Think Rockhampton might be about the right, and you can apply for special entry into Fionas FNQ. But I'm from the Kimberley so I better not poke the possum to hard", "label": 1}, "t108": {"id": "1250353767377072129", "username": "weXploretravel", "date": "2020-04-15 09:22:23+00:00", "text": "I dunno how to take that which side of loopy are all those above the southern border of North Qld.", "label": 0}, "t109": {"id": "1250352628820619271", "username": "weXploretravel", "date": "2020-04-15 09:17:51+00:00", "text": "Big Italian community in Townsville? Were Italian immigrants into the Cane farming I dunno I'm asking the question.", "label": 0}, "t110": {"id": "1250351880456138753", "username": "weXploretravel", "date": "2020-04-15 09:14:53+00:00", "text": "Do you reckon she has a higher calling", "label": 0}, "t111": {"id": "1250349847401517056", "username": "The_Patriot_81", "date": "2020-04-15 09:06:48+00:00", "text": "I normally agree with you Sydney but this is needed right now. People arn not listening so i say fine them and fine then big.", "label": 1}, "t112": {"id": "1250348340828467201", "username": "Bel52958381", "date": "2020-04-15 09:00:49+00:00", "text": "Damnnnn! I wanted to buy that the other day but I didn\u2019t have 1mil bells haha", "label": 1}, "t113": {"id": "1250348014062817285", "username": "downunderguy2", "date": "2020-04-15 08:59:31+00:00", "text": "Makes a nice change from the depressing news!!", "label": 0}, "t114": {"id": "1250347620439998469", "username": "Bel52958381", "date": "2020-04-15 08:57:57+00:00", "text": "For sure!", "label": 0}, "t115": {"id": "1250346429555470337", "username": "outbacktesla", "date": "2020-04-15 08:53:13+00:00", "text": "-16.2213000, 128.3590000 is not a catchy name but my eyes never tired of WA's natural beauty #EVeXploreAus19 @Tesla #thisisWA #virtualtravelpic.twitter.com/140Sz8jtnH", "label": 1}, "t116": {"id": "1250345871146774529", "username": "downunderguy2", "date": "2020-04-15 08:51:00+00:00", "text": "Here is a weather update from Brisbane, Australia. We are now well into Autumn. Temperatures are Celsius.pic.twitter.com/U0W1Tz74YO", "label": 0}, "t117": {"id": "1250341040193589248", "username": "PeroNasteski", "date": "2020-04-15 08:31:48+00:00", "text": "Why doesn\u2019t Gladys tell the truth and nail Duttons arse to the floor instead of calling for some lame inquire she got railroaded by Morrison on the bushfire crisis and now getting shit on again by Dutton and Morrison,grow some courage woman and stand up for your selfhttps://twitter.com/Margforequality/status/1250189017540247553 \u2026", "label": -1}, "t118": {"id": "1250335724018126856", "username": "AnthonyJMConroy", "date": "2020-04-15 08:10:41+00:00", "text": "This from a man who no one would hire anywhere bar on Government Teat #HeIsNotTheMessiahKevin #Auspol #FailedLaborPmhttps://twitter.com/MrKRudd/status/1250309831715467268 \u2026", "label": 0}, "t119": {"id": "1250333574739267587", "username": "rayscafidi", "date": "2020-04-15 08:02:08+00:00", "text": "Your a heart breaker..It's either me or your Dog...... Minty.https://twitter.com/viviennelaw_x/status/1250290666040487936 \u2026", "label": 0}, "t120": {"id": "1250333268743872512", "username": "rayscafidi", "date": "2020-04-15 08:00:55+00:00", "text": "@Knog Best Wishes to Michelle .Who was on the Millionaire Show..She came over so http://well.Best Wishes From Mission beach Qldpic.twitter.com/v6xkpkReNY", "label": 1}, "t121": {"id": "1250332841302323200", "username": "GoodremFan", "date": "2020-04-15 07:59:14+00:00", "text": "Such a perfect song for this situation right now.https://open.spotify.com/track/3JOVTQ5h8HGFnDdp4VT3MP?si=x0qFi4PYSdW9e2AfKK7SpA \u2026", "label": 1}, "t122": {"id": "1250331965300957189", "username": "PetehugauH", "date": "2020-04-15 07:55:45+00:00", "text": "Luck he wasn\u2019t in the USAhttps://twitter.com/OzraeliAvi/status/1250317556189028354 \u2026", "label": 0}, "t123": {"id": "1250329105985228801", "username": "PeroNasteski", "date": "2020-04-15 07:44:23+00:00", "text": "No mike there\u2019s a higher Price to pay if the go to school ,don\u2019t get on that bandwagon you are to smart for thathttps://twitter.com/MikeCarlton01/status/1250287509986086914 \u2026", "label": 0}, "t124": {"id": "1250326789567602689", "username": "GoodremFan", "date": "2020-04-15 07:35:11+00:00", "text": "My fianc\u00e9e would be irate if I don\u2019t make it to Cairns for Christmas #DamnThisVirus", "label": -1}, "t125": {"id": "1250326228545859586", "username": "GoodremFan", "date": "2020-04-15 07:32:57+00:00", "text": "I hope it\u2019s all good for @NZWarriors. #NRL", "label": 1}, "t126": {"id": "1250325487202648071", "username": "GoodremFan", "date": "2020-04-15 07:30:00+00:00", "text": "Just imagine being called a couch potato because of not doing much in this situation it\u2019s out of our hands and it\u2019s all we can do is to stay safe at home anyway.", "label": 0}, "t127": {"id": "1250321537627901954", "username": "weXploretravel", "date": "2020-04-15 07:14:19+00:00", "text": "Was it you @bouta_nt flying that bird, checking the fence line? We all want to know if your missing your calling", "label": 0}, "t128": {"id": "1250316301295185920", "username": "mickbatty", "date": "2020-04-15 06:53:30+00:00", "text": "I'm getting so phuking over the Trump bashers. What a pack of TDS suffering snouts.", "label": 0}, "t129": {"id": "1250314866734161920", "username": "realTomLiu", "date": "2020-04-15 06:47:48+00:00", "text": "Good on ya @realDonaldTrumphttps://twitter.com/QuickTake/status/1250187785601978374 \u2026", "label": 0}, "t130": {"id": "1250312912268226560", "username": "lifeadvicebotto", "date": "2020-04-15 06:40:02+00:00", "text": "I will have order in this court. Order! Order, please!", "label": 0}, "t131": {"id": "1250310821554446336", "username": "mickbatty", "date": "2020-04-15 06:31:44+00:00", "text": "Water wars a can of worms for Coalition and Labor https://www.farmonline.com.au/story/6086425/water-wars-a-can-of-worms-for-coalition-and-labor/?cs=4698 \u2026 via @FarmOnline", "label": -1}, "t132": {"id": "1250304668036509696", "username": "ivan_steinhardt", "date": "2020-04-15 06:07:17+00:00", "text": "Because we need to look after our country first not throw money to an organization who does not perform anything that benefits Australia", "label": 0}, "t133": {"id": "1250304241614217217", "username": "Static7s", "date": "2020-04-15 06:05:35+00:00", "text": "Congratulations", "label": 1}, "t134": {"id": "1250303109470883843", "username": "auroralovesphil", "date": "2020-04-15 06:01:05+00:00", "text": "Oh I\u2019m just being judgmental. I don\u2019t understand the mental health effects pic.twitter.com/JzuiVG9lvD", "label": 0}, "t135": {"id": "1250302818746920966", "username": "Static7s", "date": "2020-04-15 05:59:56+00:00", "text": "@kv8 thank you", "label": 0}, "t136": {"id": "1250302546318471168", "username": "Static7s", "date": "2020-04-15 05:58:51+00:00", "text": "@kv8 I came but didn\u2019t contribute, this is my tribute peace out", "label": 1}, "t137": {"id": "1250300625117569026", "username": "auroralovesphil", "date": "2020-04-15 05:51:13+00:00", "text": "ARRRGGGHHH. Seriously, they are saying that a 22 year old is not old enough to deal with this???? I had my first kid at 22 ffspic.twitter.com/3YliHuCfxB", "label": 0}, "t138": {"id": "1250294355165773824", "username": "Cathrinmachin", "date": "2020-04-15 05:26:18+00:00", "text": "Oh damn, I thi k my galaxy chandelier needs to be far bigger according to this https://twitter.com/SpaceAusDotCom/status/1250222704445120513 \u2026", "label": 0}, "t139": {"id": "1250293347194814465", "username": "Cathrinmachin", "date": "2020-04-15 05:22:17+00:00", "text": "Well I mean technically it\u2019s a photo of a print of a photo of a painting of a photo. Haha sometimes I\u2019m my own worst enemy", "label": -1}, "t140": {"id": "1250293023654555649", "username": "Cathrinmachin", "date": "2020-04-15 05:21:00+00:00", "text": "Ooh that galaxy one is of andromeda :) I actually painted it as a commission for one of the executives at prominent rocket company", "label": 1}, "t141": {"id": "1250290537652842502", "username": "Static7s", "date": "2020-04-15 05:11:08+00:00", "text": "Could you spare me ?", "label": 0}, "t142": {"id": "1250290432291946496", "username": "Static7s", "date": "2020-04-15 05:10:42+00:00", "text": "You sweetheart. Shhh", "label": 1}, "t143": {"id": "1250290203144499205", "username": "Static7s", "date": "2020-04-15 05:09:48+00:00", "text": "So true and they let you. No pic.twitter.com/DyLLZPfSaO", "label": 0}, "t144": {"id": "1250289712717115392", "username": "Static7s", "date": "2020-04-15 05:07:51+00:00", "text": "You\u2019re awesome. Thanks", "label": 1}, "t145": {"id": "1250289437705003008", "username": "Static7s", "date": "2020-04-15 05:06:45+00:00", "text": "Get nekked.", "label": 0}, "t146": {"id": "1250289195643371527", "username": "Static7s", "date": "2020-04-15 05:05:48+00:00", "text": "I\u2019m allergic to cats, don\u2019t ever come near me. Let me stay though please. x", "label": 0}, "t147": {"id": "1250287885858656256", "username": "Globlfreestyle", "date": "2020-04-15 05:00:35+00:00", "text": "Pretty things that make you feel special. Shop @Globlfreestylepic.twitter.com/3Ssw9v13JC", "label": 1}, "t148": {"id": "1250285009983795204", "username": "DamonBlakeOz", "date": "2020-04-15 04:49:10+00:00", "text": "Please stay safe X", "label": 1}, "t149": {"id": "1250284902064345090", "username": "DamonBlakeOz", "date": "2020-04-15 04:48:44+00:00", "text": "Isolate from your loved ones Annie..", "label": 0}, "t150": {"id": "1250274243448721410", "username": "downunderguy2", "date": "2020-04-15 04:06:23+00:00", "text": "I am not going to argue with you. If you are a serious trump supporter we have nothing further to discuss. Have a nice life...", "label": 1}, "t151": {"id": "1250273381129154561", "username": "PooleKaytlyn", "date": "2020-04-15 04:02:57+00:00", "text": "Selfie I took last night #selfie #latenight #messyhair #hair #lips #girlpic.twitter.com/STVstjiCGk", "label": 0}, "t152": {"id": "1250271745166082048", "username": "FijiSchProjects", "date": "2020-04-15 03:56:27+00:00", "text": "STAND YOUR GROUND and do not give into unhealthy demands @pmc_gov_au @healthgovau @AusBorderForce @NTPHN @Malarndirri19 @SenatorDodson @indigenous_gov @ABCIndigenous Australian government settles cruise ship lawsuit fighting coronavirus orderhttps://www.theguardian.com/world/2020/apr/15/australian-government-settles-cruise-ship-lawsuit-fighting-coronavirus-order \u2026", "label": 0}, "t153": {"id": "1250270971904143362", "username": "Hatsbyfelicity", "date": "2020-04-15 03:53:23+00:00", "text": "I\u2019ve been wondering the exact same thing", "label": 0}, "t154": {"id": "1250268656614793220", "username": "ciaratollanxx", "date": "2020-04-15 03:44:11+00:00", "text": "Jurassic Mountain Resort, Thailand. Siamese Carp Carnage https://youtu.be/Qju2aKGfhZo featuring my unreal camera, fishing & waitressing skills #fishing #Thailand", "label": 0}, "t155": {"id": "1250254052597706752", "username": "trufflehuffer", "date": "2020-04-15 02:46:09+00:00", "text": "wishes the wing that\u2019s made its home on @POTUS\u2019s head would fly him off to the sun ... #WHO", "label": 0}, "t156": {"id": "1250249878757728256", "username": "infinitexrauhl", "date": "2020-04-15 02:29:34+00:00", "text": "Today is my parents 25th wedding anniversary pic.twitter.com/Zn0mlN6FB2", "label": 0}, "t157": {"id": "1250249775733035015", "username": "weXploretravel", "date": "2020-04-15 02:29:09+00:00", "text": "Never pays to be last in line.", "label": 0}, "t158": {"id": "1250249185569337345", "username": "weXploretravel", "date": "2020-04-15 02:26:49+00:00", "text": "Gee, that's rubbing salt into the wound. Head selector must have been from NSW", "label": 0}, "t159": {"id": "1250248745662341120", "username": "weXploretravel", "date": "2020-04-15 02:25:04+00:00", "text": "Huh, there you go. Doesn't surprise me I guess.", "label": 0}, "t160": {"id": "1250246223153397760", "username": "weXploretravel", "date": "2020-04-15 02:15:02+00:00", "text": "The next thing to be stockpiled. Bet Harvey Norman has a run on sales of chest freezes.https://twitter.com/Forbes/status/1250185461567537157 \u2026", "label": 0}, "t161": {"id": "1250243926918721536", "username": "weXploretravel", "date": "2020-04-15 02:05:55+00:00", "text": "Huh, what a dill I am, meant to say appreciated.", "label": 1}, "t162": {"id": "1250243006742925313", "username": "tols03", "date": "2020-04-15 02:02:15+00:00", "text": "AND I AM HERE FOR THISSSS. The only energy I want in 2020", "label": 0}, "t163": {"id": "1250242189705256960", "username": "BPEarth", "date": "2020-04-15 01:59:01+00:00", "text": "#32998 Victoria River NT 0852, Australia map: https://www.google.com/maps/place/-16.6612327539,131.07028548/data=!3m1!1e3!4m2!3m1!1s0x0:0x0 \u2026pic.twitter.com/pxZITTOj49", "label": 0}, "t164": {"id": "1250240673611038720", "username": "Bel52958381", "date": "2020-04-15 01:52:59+00:00", "text": "Just sent request", "label": 0}, "t165": {"id": "1250239573973598208", "username": "Bel52958381", "date": "2020-04-15 01:48:37+00:00", "text": "Do u need me to send switch code again?", "label": 0}, "t166": {"id": "1250238294018781184", "username": "Bel52958381", "date": "2020-04-15 01:43:32+00:00", "text": "I\u2019m opening up now", "label": 0}, "t167": {"id": "1250238032873009152", "username": "Bel52958381", "date": "2020-04-15 01:42:29+00:00", "text": "Yeah that\u2019s cool r u ready now?", "label": 1}, "t168": {"id": "1250237819949203456", "username": "weXploretravel", "date": "2020-04-15 01:41:39+00:00", "text": "Thanks, Paul, most appropriated. What state did he come from?", "label": 0}, "t169": {"id": "1250237432252862464", "username": "weXploretravel", "date": "2020-04-15 01:40:06+00:00", "text": "I visited all the locations featured on extended trip of U.S last year. My memories and pics are the polar opposite to the eerie emptiness that is at present.https://twitter.com/Escape_team/status/1250232600435642370 \u2026", "label": -1}, "t170": {"id": "1250234024330551297", "username": "sanchar303", "date": "2020-04-15 01:26:34+00:00", "text": "People simply defame death Life is the one that gives the suffering", "label": -1}, "t171": {"id": "1250226658147065856", "username": "trufflehuffer", "date": "2020-04-15 00:57:18+00:00", "text": "@POTUS is well and truly getting off on killing people! The guy needs locking up. Forever. Alone.https://twitter.com/abcnews/status/1250190380399640576 \u2026", "label": 0}, "t172": {"id": "1250226253010890752", "username": "Sarahlina84", "date": "2020-04-15 00:55:41+00:00", "text": "What teacher hasn\u2019t returned to the classroom My husband hasn\u2019t had a break yet - between constantly updating his parents, learning the new online platforms, double the work as some of our kids don\u2019t have computers, and worrying about his students. Oh but will please go backhttps://twitter.com/newscomauHQ/status/1250160065480450054 \u2026", "label": 0}, "t173": {"id": "1250224260951363584", "username": "helenmw2009", "date": "2020-04-15 00:47:46+00:00", "text": "What about 2nd breakfast?", "label": 0}, "t174": {"id": "1250223596175155201", "username": "CottonEyeAndy", "date": "2020-04-15 00:45:08+00:00", "text": "Thank you Joe that\u2019s my son your talking about I\u2019m proud of my wife bess @cottonwife for reaching out. Thanks for that it means a lot.", "label": 1}, "t175": {"id": "1250223182721646593", "username": "weXploretravel", "date": "2020-04-15 00:43:29+00:00", "text": "That's it in a nutshell, hey. Sums it up.", "label": 0}, "t176": {"id": "1250221419884994561", "username": "weXploretravel", "date": "2020-04-15 00:36:29+00:00", "text": "@the_summer_game Hey Paul, I recognize all the names on the scoreboard in this 1971 shot except the opening bat Eastwood can you enlighten me please.https://twitter.com/KnightkingYCBM/status/1249943945720680448 \u2026", "label": 1}, "t177": {"id": "1250221040761860102", "username": "P_sudzo", "date": "2020-04-15 00:34:58+00:00", "text": "#\u81ea\u5b85\u65c5\u884c 2019\u5e7411\u6708 Girraween Nationl Park \uff08QLD\uff09pic.twitter.com/idF1VjDn8y", "label": 0}, "t178": {"id": "1250220762339799040", "username": "weXploretravel", "date": "2020-04-15 00:33:52+00:00", "text": "Only three shirts & three hats between them all. It was another time another place to today - the games sorta the same.https://twitter.com/KnightkingYCBM/status/1249943945720680448 \u2026", "label": 0}, "t179": {"id": "1250220700893433857", "username": "FilippoGelada", "date": "2020-04-15 00:33:37+00:00", "text": "Rise and shine! Great beginning of the day with 15 min abs and cardio workout by jordanyeohfitness followed by 30 min heavy bag training by @NBFitness Week 3 of my boxing training is going great, feeling\u2026 https://www.instagram.com/p/B--0UWKhpdy/?igshid=1udeqhssuyp9s \u2026", "label": 1}, "t180": {"id": "1250219218156412928", "username": "weXploretravel", "date": "2020-04-15 00:27:44+00:00", "text": "You flying that bird Bouta?", "label": 0}, "t181": {"id": "1250218403807113216", "username": "weXploretravel", "date": "2020-04-15 00:24:30+00:00", "text": "@SteveBackshall Hey Steve, have you ever conducted a bite gauge test on a Tassie Devil?", "label": -1}, "t182": {"id": "1250217581367066624", "username": "weXploretravel", "date": "2020-04-15 00:21:13+00:00", "text": "Australia grows lots of stuff, doesn't mean you see it on the shelf. I was buying Australian & other countries produce in Walmart & Publix supermarkets in U.S - Go figure. All comes down to dollars not loyalty to a countries farmers.", "label": 0}, "t183": {"id": "1250213569993388033", "username": "weXploretravel", "date": "2020-04-15 00:05:17+00:00", "text": "Home made Hommus Flour, Soap, Hand Sanitizer, Toilet Paper, Alcohol. Pasta, Rice & Can foods (long shelf life)", "label": 0}}